{
	"@type":"Subset",
	"Name":"Reporting Cube FAP to Reporting_Target1",
	"Elements":
	[
		{
			"@id":"Dimensions('Company')/Hierarchies('Company')/Elements('@None')"
		},
		{
			"@id":"Dimensions('Company')/Hierarchies('Company')/Elements('Q.SUBSTA')"
		},
		{
			"@id":"Dimensions('Company')/Hierarchies('Company')/Elements('SUBSTA')"
		},
		{
			"@id":"Dimensions('Company')/Hierarchies('Company')/Elements('S910GA')"
		},
		{
			"@id":"Dimensions('Company')/Hierarchies('Company')/Elements('S9100FAP_')"
		},
		{
			"@id":"Dimensions('Company')/Hierarchies('Company')/Elements('S9100')"
		},
		{
			"@id":"Dimensions('Company')/Hierarchies('Company')/Elements('S901GA')"
		},
		{
			"@id":"Dimensions('Company')/Hierarchies('Company')/Elements('S9010FAP_')"
		},
		{
			"@id":"Dimensions('Company')/Hierarchies('Company')/Elements('S9010')"
		},
		{
			"@id":"Dimensions('Company')/Hierarchies('Company')/Elements('S900GA')"
		},
		{
			"@id":"Dimensions('Company')/Hierarchies('Company')/Elements('S9000FAP_')"
		},
		{
			"@id":"Dimensions('Company')/Hierarchies('Company')/Elements('S9000')"
		},
		{
			"@id":"Dimensions('Company')/Hierarchies('Company')/Elements('S615GA')"
		},
		{
			"@id":"Dimensions('Company')/Hierarchies('Company')/Elements('S6150FAP_')"
		},
		{
			"@id":"Dimensions('Company')/Hierarchies('Company')/Elements('S6150')"
		},
		{
			"@id":"Dimensions('Company')/Hierarchies('Company')/Elements('S605GA')"
		},
		{
			"@id":"Dimensions('Company')/Hierarchies('Company')/Elements('S6050FAP_')"
		},
		{
			"@id":"Dimensions('Company')/Hierarchies('Company')/Elements('S6050')"
		},
		{
			"@id":"Dimensions('Company')/Hierarchies('Company')/Elements('S600GA')"
		},
		{
			"@id":"Dimensions('Company')/Hierarchies('Company')/Elements('S6000FAP_')"
		},
		{
			"@id":"Dimensions('Company')/Hierarchies('Company')/Elements('S6000')"
		},
		{
			"@id":"Dimensions('Company')/Hierarchies('Company')/Elements('S590GA')"
		},
		{
			"@id":"Dimensions('Company')/Hierarchies('Company')/Elements('S5900FAP_')"
		},
		{
			"@id":"Dimensions('Company')/Hierarchies('Company')/Elements('S5900')"
		},
		{
			"@id":"Dimensions('Company')/Hierarchies('Company')/Elements('Q.S585GC')"
		},
		{
			"@id":"Dimensions('Company')/Hierarchies('Company')/Elements('S585GC')"
		},
		{
			"@id":"Dimensions('Company')/Hierarchies('Company')/Elements('S585GA')"
		},
		{
			"@id":"Dimensions('Company')/Hierarchies('Company')/Elements('S5852FAP_')"
		},
		{
			"@id":"Dimensions('Company')/Hierarchies('Company')/Elements('S5852')"
		},
		{
			"@id":"Dimensions('Company')/Hierarchies('Company')/Elements('S5851FAP_')"
		},
		{
			"@id":"Dimensions('Company')/Hierarchies('Company')/Elements('S5851')"
		},
		{
			"@id":"Dimensions('Company')/Hierarchies('Company')/Elements('S5850FAP_')"
		},
		{
			"@id":"Dimensions('Company')/Hierarchies('Company')/Elements('S5850')"
		},
		{
			"@id":"Dimensions('Company')/Hierarchies('Company')/Elements('S581GA')"
		},
		{
			"@id":"Dimensions('Company')/Hierarchies('Company')/Elements('Q.S580GA')"
		},
		{
			"@id":"Dimensions('Company')/Hierarchies('Company')/Elements('S580GA')"
		},
		{
			"@id":"Dimensions('Company')/Hierarchies('Company')/Elements('Q.S5800')"
		},
		{
			"@id":"Dimensions('Company')/Hierarchies('Company')/Elements('S5800FAP_')"
		},
		{
			"@id":"Dimensions('Company')/Hierarchies('Company')/Elements('S5800')"
		},
		{
			"@id":"Dimensions('Company')/Hierarchies('Company')/Elements('S574GA')"
		},
		{
			"@id":"Dimensions('Company')/Hierarchies('Company')/Elements('S5740FAP_')"
		},
		{
			"@id":"Dimensions('Company')/Hierarchies('Company')/Elements('S5740')"
		},
		{
			"@id":"Dimensions('Company')/Hierarchies('Company')/Elements('S573GA')"
		},
		{
			"@id":"Dimensions('Company')/Hierarchies('Company')/Elements('S5730FAP_')"
		},
		{
			"@id":"Dimensions('Company')/Hierarchies('Company')/Elements('S5730')"
		},
		{
			"@id":"Dimensions('Company')/Hierarchies('Company')/Elements('S565GA')"
		},
		{
			"@id":"Dimensions('Company')/Hierarchies('Company')/Elements('S5650FAP_')"
		},
		{
			"@id":"Dimensions('Company')/Hierarchies('Company')/Elements('S5650')"
		},
		{
			"@id":"Dimensions('Company')/Hierarchies('Company')/Elements('S560GA')"
		},
		{
			"@id":"Dimensions('Company')/Hierarchies('Company')/Elements('S5600FAP_')"
		},
		{
			"@id":"Dimensions('Company')/Hierarchies('Company')/Elements('S5600')"
		},
		{
			"@id":"Dimensions('Company')/Hierarchies('Company')/Elements('S550GA')"
		},
		{
			"@id":"Dimensions('Company')/Hierarchies('Company')/Elements('S5500FAP_')"
		},
		{
			"@id":"Dimensions('Company')/Hierarchies('Company')/Elements('S5500')"
		},
		{
			"@id":"Dimensions('Company')/Hierarchies('Company')/Elements('S546GA')"
		},
		{
			"@id":"Dimensions('Company')/Hierarchies('Company')/Elements('S5460FAP_')"
		},
		{
			"@id":"Dimensions('Company')/Hierarchies('Company')/Elements('S5460')"
		},
		{
			"@id":"Dimensions('Company')/Hierarchies('Company')/Elements('S545GA')"
		},
		{
			"@id":"Dimensions('Company')/Hierarchies('Company')/Elements('S5450FAP_')"
		},
		{
			"@id":"Dimensions('Company')/Hierarchies('Company')/Elements('S5450')"
		},
		{
			"@id":"Dimensions('Company')/Hierarchies('Company')/Elements('S5350G')"
		},
		{
			"@id":"Dimensions('Company')/Hierarchies('Company')/Elements('S5350FAP_')"
		},
		{
			"@id":"Dimensions('Company')/Hierarchies('Company')/Elements('S5350')"
		},
		{
			"@id":"Dimensions('Company')/Hierarchies('Company')/Elements('S532GA')"
		},
		{
			"@id":"Dimensions('Company')/Hierarchies('Company')/Elements('S5320FAP_')"
		},
		{
			"@id":"Dimensions('Company')/Hierarchies('Company')/Elements('S5320')"
		},
		{
			"@id":"Dimensions('Company')/Hierarchies('Company')/Elements('S531GA')"
		},
		{
			"@id":"Dimensions('Company')/Hierarchies('Company')/Elements('S5310FAP_')"
		},
		{
			"@id":"Dimensions('Company')/Hierarchies('Company')/Elements('S5310')"
		},
		{
			"@id":"Dimensions('Company')/Hierarchies('Company')/Elements('S530GA')"
		},
		{
			"@id":"Dimensions('Company')/Hierarchies('Company')/Elements('S5300FAP_')"
		},
		{
			"@id":"Dimensions('Company')/Hierarchies('Company')/Elements('S5300')"
		},
		{
			"@id":"Dimensions('Company')/Hierarchies('Company')/Elements('S520GA')"
		},
		{
			"@id":"Dimensions('Company')/Hierarchies('Company')/Elements('S5200FAP_')"
		},
		{
			"@id":"Dimensions('Company')/Hierarchies('Company')/Elements('S5200')"
		},
		{
			"@id":"Dimensions('Company')/Hierarchies('Company')/Elements('S519GA')"
		},
		{
			"@id":"Dimensions('Company')/Hierarchies('Company')/Elements('S5190FAP_')"
		},
		{
			"@id":"Dimensions('Company')/Hierarchies('Company')/Elements('S5190')"
		},
		{
			"@id":"Dimensions('Company')/Hierarchies('Company')/Elements('S514GC')"
		},
		{
			"@id":"Dimensions('Company')/Hierarchies('Company')/Elements('S514GA')"
		},
		{
			"@id":"Dimensions('Company')/Hierarchies('Company')/Elements('S5145FAP_')"
		},
		{
			"@id":"Dimensions('Company')/Hierarchies('Company')/Elements('S5145')"
		},
		{
			"@id":"Dimensions('Company')/Hierarchies('Company')/Elements('S5140FAP_')"
		},
		{
			"@id":"Dimensions('Company')/Hierarchies('Company')/Elements('S5140')"
		},
		{
			"@id":"Dimensions('Company')/Hierarchies('Company')/Elements('S512GA')"
		},
		{
			"@id":"Dimensions('Company')/Hierarchies('Company')/Elements('S5120FAP_')"
		},
		{
			"@id":"Dimensions('Company')/Hierarchies('Company')/Elements('S5120')"
		},
		{
			"@id":"Dimensions('Company')/Hierarchies('Company')/Elements('S510GA')"
		},
		{
			"@id":"Dimensions('Company')/Hierarchies('Company')/Elements('S5100FAP_')"
		},
		{
			"@id":"Dimensions('Company')/Hierarchies('Company')/Elements('S5100')"
		},
		{
			"@id":"Dimensions('Company')/Hierarchies('Company')/Elements('S505GA')"
		},
		{
			"@id":"Dimensions('Company')/Hierarchies('Company')/Elements('S5050FAP_')"
		},
		{
			"@id":"Dimensions('Company')/Hierarchies('Company')/Elements('S5050')"
		},
		{
			"@id":"Dimensions('Company')/Hierarchies('Company')/Elements('S502GA')"
		},
		{
			"@id":"Dimensions('Company')/Hierarchies('Company')/Elements('S5020FAP_')"
		},
		{
			"@id":"Dimensions('Company')/Hierarchies('Company')/Elements('S5020')"
		},
		{
			"@id":"Dimensions('Company')/Hierarchies('Company')/Elements('S501GA')"
		},
		{
			"@id":"Dimensions('Company')/Hierarchies('Company')/Elements('S5010FAP_')"
		},
		{
			"@id":"Dimensions('Company')/Hierarchies('Company')/Elements('S5010')"
		},
		{
			"@id":"Dimensions('Company')/Hierarchies('Company')/Elements('S500GA')"
		},
		{
			"@id":"Dimensions('Company')/Hierarchies('Company')/Elements('S5000FAP_')"
		},
		{
			"@id":"Dimensions('Company')/Hierarchies('Company')/Elements('S5000')"
		},
		{
			"@id":"Dimensions('Company')/Hierarchies('Company')/Elements('S4410FAP_')"
		},
		{
			"@id":"Dimensions('Company')/Hierarchies('Company')/Elements('S4410')"
		},
		{
			"@id":"Dimensions('Company')/Hierarchies('Company')/Elements('S440GA')"
		},
		{
			"@id":"Dimensions('Company')/Hierarchies('Company')/Elements('S4400FAP_')"
		},
		{
			"@id":"Dimensions('Company')/Hierarchies('Company')/Elements('S4400')"
		},
		{
			"@id":"Dimensions('Company')/Hierarchies('Company')/Elements('S430GA')"
		},
		{
			"@id":"Dimensions('Company')/Hierarchies('Company')/Elements('S4300FAP_')"
		},
		{
			"@id":"Dimensions('Company')/Hierarchies('Company')/Elements('S4300')"
		},
		{
			"@id":"Dimensions('Company')/Hierarchies('Company')/Elements('S420GA')"
		},
		{
			"@id":"Dimensions('Company')/Hierarchies('Company')/Elements('S4200FAP_')"
		},
		{
			"@id":"Dimensions('Company')/Hierarchies('Company')/Elements('S4200')"
		},
		{
			"@id":"Dimensions('Company')/Hierarchies('Company')/Elements('S410GC')"
		},
		{
			"@id":"Dimensions('Company')/Hierarchies('Company')/Elements('S410GA')"
		},
		{
			"@id":"Dimensions('Company')/Hierarchies('Company')/Elements('S4100FAP_')"
		},
		{
			"@id":"Dimensions('Company')/Hierarchies('Company')/Elements('S4100')"
		},
		{
			"@id":"Dimensions('Company')/Hierarchies('Company')/Elements('S300GA')"
		},
		{
			"@id":"Dimensions('Company')/Hierarchies('Company')/Elements('S3000FAP_')"
		},
		{
			"@id":"Dimensions('Company')/Hierarchies('Company')/Elements('S3000')"
		},
		{
			"@id":"Dimensions('Company')/Hierarchies('Company')/Elements('S220GA')"
		},
		{
			"@id":"Dimensions('Company')/Hierarchies('Company')/Elements('S2200FAP_')"
		},
		{
			"@id":"Dimensions('Company')/Hierarchies('Company')/Elements('S2200')"
		},
		{
			"@id":"Dimensions('Company')/Hierarchies('Company')/Elements('S210GA')"
		},
		{
			"@id":"Dimensions('Company')/Hierarchies('Company')/Elements('S2100FAP_')"
		},
		{
			"@id":"Dimensions('Company')/Hierarchies('Company')/Elements('S2100')"
		},
		{
			"@id":"Dimensions('Company')/Hierarchies('Company')/Elements('S205GA')"
		},
		{
			"@id":"Dimensions('Company')/Hierarchies('Company')/Elements('S2050FAP_')"
		},
		{
			"@id":"Dimensions('Company')/Hierarchies('Company')/Elements('S2050')"
		},
		{
			"@id":"Dimensions('Company')/Hierarchies('Company')/Elements('S200GA')"
		},
		{
			"@id":"Dimensions('Company')/Hierarchies('Company')/Elements('S2000FAP_')"
		},
		{
			"@id":"Dimensions('Company')/Hierarchies('Company')/Elements('S2000')"
		},
		{
			"@id":"Dimensions('Company')/Hierarchies('Company')/Elements('S100GA')"
		},
		{
			"@id":"Dimensions('Company')/Hierarchies('Company')/Elements('S1000FAP_')"
		},
		{
			"@id":"Dimensions('Company')/Hierarchies('Company')/Elements('S1000')"
		},
		{
			"@id":"Dimensions('Company')/Hierarchies('Company')/Elements('P6204G')"
		},
		{
			"@id":"Dimensions('Company')/Hierarchies('Company')/Elements('P6204')"
		},
		{
			"@id":"Dimensions('Company')/Hierarchies('Company')/Elements('P6203G')"
		},
		{
			"@id":"Dimensions('Company')/Hierarchies('Company')/Elements('P6203')"
		},
		{
			"@id":"Dimensions('Company')/Hierarchies('Company')/Elements('P6202G')"
		},
		{
			"@id":"Dimensions('Company')/Hierarchies('Company')/Elements('P6202')"
		},
		{
			"@id":"Dimensions('Company')/Hierarchies('Company')/Elements('P6201G')"
		},
		{
			"@id":"Dimensions('Company')/Hierarchies('Company')/Elements('P6201')"
		},
		{
			"@id":"Dimensions('Company')/Hierarchies('Company')/Elements('P6200')"
		},
		{
			"@id":"Dimensions('Company')/Hierarchies('Company')/Elements('P540GA')"
		},
		{
			"@id":"Dimensions('Company')/Hierarchies('Company')/Elements('P5402G')"
		},
		{
			"@id":"Dimensions('Company')/Hierarchies('Company')/Elements('P5402')"
		},
		{
			"@id":"Dimensions('Company')/Hierarchies('Company')/Elements('P5401G')"
		},
		{
			"@id":"Dimensions('Company')/Hierarchies('Company')/Elements('P5401')"
		},
		{
			"@id":"Dimensions('Company')/Hierarchies('Company')/Elements('P5400')"
		},
		{
			"@id":"Dimensions('Company')/Hierarchies('Company')/Elements('P1000')"
		},
		{
			"@id":"Dimensions('Company')/Hierarchies('Company')/Elements('Q.OCEATA')"
		},
		{
			"@id":"Dimensions('Company')/Hierarchies('Company')/Elements('OCEATA')"
		},
		{
			"@id":"Dimensions('Company')/Hierarchies('Company')/Elements('Q.MOJOTA')"
		},
		{
			"@id":"Dimensions('Company')/Hierarchies('Company')/Elements('MOJOTA')"
		},
		{
			"@id":"Dimensions('Company')/Hierarchies('Company')/Elements('Q.MIMITA')"
		},
		{
			"@id":"Dimensions('Company')/Hierarchies('Company')/Elements('MIMITA')"
		},
		{
			"@id":"Dimensions('Company')/Hierarchies('Company')/Elements('M910GA')"
		},
		{
			"@id":"Dimensions('Company')/Hierarchies('Company')/Elements('M9100FAP_')"
		},
		{
			"@id":"Dimensions('Company')/Hierarchies('Company')/Elements('M9100')"
		},
		{
			"@id":"Dimensions('Company')/Hierarchies('Company')/Elements('M901GA')"
		},
		{
			"@id":"Dimensions('Company')/Hierarchies('Company')/Elements('M9010FAP_')"
		},
		{
			"@id":"Dimensions('Company')/Hierarchies('Company')/Elements('M9010')"
		},
		{
			"@id":"Dimensions('Company')/Hierarchies('Company')/Elements('M900GA')"
		},
		{
			"@id":"Dimensions('Company')/Hierarchies('Company')/Elements('M900C')"
		},
		{
			"@id":"Dimensions('Company')/Hierarchies('Company')/Elements('M9000FAP_')"
		},
		{
			"@id":"Dimensions('Company')/Hierarchies('Company')/Elements('M9000')"
		},
		{
			"@id":"Dimensions('Company')/Hierarchies('Company')/Elements('M640GA')"
		},
		{
			"@id":"Dimensions('Company')/Hierarchies('Company')/Elements('M6400FAP_')"
		},
		{
			"@id":"Dimensions('Company')/Hierarchies('Company')/Elements('M6400')"
		},
		{
			"@id":"Dimensions('Company')/Hierarchies('Company')/Elements('M635GA')"
		},
		{
			"@id":"Dimensions('Company')/Hierarchies('Company')/Elements('M6350FAP_')"
		},
		{
			"@id":"Dimensions('Company')/Hierarchies('Company')/Elements('M6350')"
		},
		{
			"@id":"Dimensions('Company')/Hierarchies('Company')/Elements('M630GA')"
		},
		{
			"@id":"Dimensions('Company')/Hierarchies('Company')/Elements('M6300FAP_')"
		},
		{
			"@id":"Dimensions('Company')/Hierarchies('Company')/Elements('M6300')"
		},
		{
			"@id":"Dimensions('Company')/Hierarchies('Company')/Elements('M620A')"
		},
		{
			"@id":"Dimensions('Company')/Hierarchies('Company')/Elements('M6200FAP_')"
		},
		{
			"@id":"Dimensions('Company')/Hierarchies('Company')/Elements('M6200')"
		},
		{
			"@id":"Dimensions('Company')/Hierarchies('Company')/Elements('M615GA')"
		},
		{
			"@id":"Dimensions('Company')/Hierarchies('Company')/Elements('M6150FAP_')"
		},
		{
			"@id":"Dimensions('Company')/Hierarchies('Company')/Elements('M6150')"
		},
		{
			"@id":"Dimensions('Company')/Hierarchies('Company')/Elements('M611GA')"
		},
		{
			"@id":"Dimensions('Company')/Hierarchies('Company')/Elements('M6110FAP_')"
		},
		{
			"@id":"Dimensions('Company')/Hierarchies('Company')/Elements('M6110')"
		},
		{
			"@id":"Dimensions('Company')/Hierarchies('Company')/Elements('M610GA')"
		},
		{
			"@id":"Dimensions('Company')/Hierarchies('Company')/Elements('M6100FAP_')"
		},
		{
			"@id":"Dimensions('Company')/Hierarchies('Company')/Elements('M6100')"
		},
		{
			"@id":"Dimensions('Company')/Hierarchies('Company')/Elements('M605GA')"
		},
		{
			"@id":"Dimensions('Company')/Hierarchies('Company')/Elements('M6050FAP_')"
		},
		{
			"@id":"Dimensions('Company')/Hierarchies('Company')/Elements('M6050')"
		},
		{
			"@id":"Dimensions('Company')/Hierarchies('Company')/Elements('M600GA')"
		},
		{
			"@id":"Dimensions('Company')/Hierarchies('Company')/Elements('M600C')"
		},
		{
			"@id":"Dimensions('Company')/Hierarchies('Company')/Elements('M6000FAP_')"
		},
		{
			"@id":"Dimensions('Company')/Hierarchies('Company')/Elements('M6000')"
		},
		{
			"@id":"Dimensions('Company')/Hierarchies('Company')/Elements('M590GA')"
		},
		{
			"@id":"Dimensions('Company')/Hierarchies('Company')/Elements('M5900FAP_')"
		},
		{
			"@id":"Dimensions('Company')/Hierarchies('Company')/Elements('M5900')"
		},
		{
			"@id":"Dimensions('Company')/Hierarchies('Company')/Elements('M5852G')"
		},
		{
			"@id":"Dimensions('Company')/Hierarchies('Company')/Elements('M5852FAP_')"
		},
		{
			"@id":"Dimensions('Company')/Hierarchies('Company')/Elements('M5852')"
		},
		{
			"@id":"Dimensions('Company')/Hierarchies('Company')/Elements('M5851G')"
		},
		{
			"@id":"Dimensions('Company')/Hierarchies('Company')/Elements('M5851FAP_')"
		},
		{
			"@id":"Dimensions('Company')/Hierarchies('Company')/Elements('M5851')"
		},
		{
			"@id":"Dimensions('Company')/Hierarchies('Company')/Elements('M5850G')"
		},
		{
			"@id":"Dimensions('Company')/Hierarchies('Company')/Elements('M5850FAP_')"
		},
		{
			"@id":"Dimensions('Company')/Hierarchies('Company')/Elements('M5850')"
		},
		{
			"@id":"Dimensions('Company')/Hierarchies('Company')/Elements('Q.M580GA')"
		},
		{
			"@id":"Dimensions('Company')/Hierarchies('Company')/Elements('M580GA')"
		},
		{
			"@id":"Dimensions('Company')/Hierarchies('Company')/Elements('Q.M5800')"
		},
		{
			"@id":"Dimensions('Company')/Hierarchies('Company')/Elements('M5800FAP_')"
		},
		{
			"@id":"Dimensions('Company')/Hierarchies('Company')/Elements('M5800')"
		},
		{
			"@id":"Dimensions('Company')/Hierarchies('Company')/Elements('Q.M5750G')"
		},
		{
			"@id":"Dimensions('Company')/Hierarchies('Company')/Elements('M5750G')"
		},
		{
			"@id":"Dimensions('Company')/Hierarchies('Company')/Elements('Q.M5750')"
		},
		{
			"@id":"Dimensions('Company')/Hierarchies('Company')/Elements('M5750FAP_')"
		},
		{
			"@id":"Dimensions('Company')/Hierarchies('Company')/Elements('M5750')"
		},
		{
			"@id":"Dimensions('Company')/Hierarchies('Company')/Elements('M574GA')"
		},
		{
			"@id":"Dimensions('Company')/Hierarchies('Company')/Elements('M5740FAP_')"
		},
		{
			"@id":"Dimensions('Company')/Hierarchies('Company')/Elements('M5740')"
		},
		{
			"@id":"Dimensions('Company')/Hierarchies('Company')/Elements('M573GA')"
		},
		{
			"@id":"Dimensions('Company')/Hierarchies('Company')/Elements('M5730FAP_')"
		},
		{
			"@id":"Dimensions('Company')/Hierarchies('Company')/Elements('M5730')"
		},
		{
			"@id":"Dimensions('Company')/Hierarchies('Company')/Elements('Q.M572GA')"
		},
		{
			"@id":"Dimensions('Company')/Hierarchies('Company')/Elements('M572GA')"
		},
		{
			"@id":"Dimensions('Company')/Hierarchies('Company')/Elements('Q.M5720')"
		},
		{
			"@id":"Dimensions('Company')/Hierarchies('Company')/Elements('M5720FAP_')"
		},
		{
			"@id":"Dimensions('Company')/Hierarchies('Company')/Elements('M5720')"
		},
		{
			"@id":"Dimensions('Company')/Hierarchies('Company')/Elements('Q.M571GA')"
		},
		{
			"@id":"Dimensions('Company')/Hierarchies('Company')/Elements('M571GA')"
		},
		{
			"@id":"Dimensions('Company')/Hierarchies('Company')/Elements('Q.M5710')"
		},
		{
			"@id":"Dimensions('Company')/Hierarchies('Company')/Elements('M5710FAP_')"
		},
		{
			"@id":"Dimensions('Company')/Hierarchies('Company')/Elements('M5710')"
		},
		{
			"@id":"Dimensions('Company')/Hierarchies('Company')/Elements('Q.M570GA')"
		},
		{
			"@id":"Dimensions('Company')/Hierarchies('Company')/Elements('M570GA')"
		},
		{
			"@id":"Dimensions('Company')/Hierarchies('Company')/Elements('M5702G')"
		},
		{
			"@id":"Dimensions('Company')/Hierarchies('Company')/Elements('M5702FAP_')"
		},
		{
			"@id":"Dimensions('Company')/Hierarchies('Company')/Elements('M5702')"
		},
		{
			"@id":"Dimensions('Company')/Hierarchies('Company')/Elements('Q.M5701G')"
		},
		{
			"@id":"Dimensions('Company')/Hierarchies('Company')/Elements('M5701G')"
		},
		{
			"@id":"Dimensions('Company')/Hierarchies('Company')/Elements('Q.M5701')"
		},
		{
			"@id":"Dimensions('Company')/Hierarchies('Company')/Elements('M5701')"
		},
		{
			"@id":"Dimensions('Company')/Hierarchies('Company')/Elements('Q.M5700')"
		},
		{
			"@id":"Dimensions('Company')/Hierarchies('Company')/Elements('M5700')"
		},
		{
			"@id":"Dimensions('Company')/Hierarchies('Company')/Elements('M565GA')"
		},
		{
			"@id":"Dimensions('Company')/Hierarchies('Company')/Elements('M5650FAP_')"
		},
		{
			"@id":"Dimensions('Company')/Hierarchies('Company')/Elements('M5650')"
		},
		{
			"@id":"Dimensions('Company')/Hierarchies('Company')/Elements('M560GA')"
		},
		{
			"@id":"Dimensions('Company')/Hierarchies('Company')/Elements('M5600FAP_')"
		},
		{
			"@id":"Dimensions('Company')/Hierarchies('Company')/Elements('M5600')"
		},
		{
			"@id":"Dimensions('Company')/Hierarchies('Company')/Elements('Q.M5550G')"
		},
		{
			"@id":"Dimensions('Company')/Hierarchies('Company')/Elements('M5550G')"
		},
		{
			"@id":"Dimensions('Company')/Hierarchies('Company')/Elements('Q.M5550')"
		},
		{
			"@id":"Dimensions('Company')/Hierarchies('Company')/Elements('M5550FAP_')"
		},
		{
			"@id":"Dimensions('Company')/Hierarchies('Company')/Elements('M5550')"
		},
		{
			"@id":"Dimensions('Company')/Hierarchies('Company')/Elements('Q.M552GA')"
		},
		{
			"@id":"Dimensions('Company')/Hierarchies('Company')/Elements('M552GA')"
		},
		{
			"@id":"Dimensions('Company')/Hierarchies('Company')/Elements('Q.M5520')"
		},
		{
			"@id":"Dimensions('Company')/Hierarchies('Company')/Elements('M5520')"
		},
		{
			"@id":"Dimensions('Company')/Hierarchies('Company')/Elements('Q.M551GA')"
		},
		{
			"@id":"Dimensions('Company')/Hierarchies('Company')/Elements('M551GA')"
		},
		{
			"@id":"Dimensions('Company')/Hierarchies('Company')/Elements('Q.M5510')"
		},
		{
			"@id":"Dimensions('Company')/Hierarchies('Company')/Elements('M5510')"
		},
		{
			"@id":"Dimensions('Company')/Hierarchies('Company')/Elements('M550GA')"
		},
		{
			"@id":"Dimensions('Company')/Hierarchies('Company')/Elements('M5500FAP_')"
		},
		{
			"@id":"Dimensions('Company')/Hierarchies('Company')/Elements('M5500')"
		},
		{
			"@id":"Dimensions('Company')/Hierarchies('Company')/Elements('M546GA')"
		},
		{
			"@id":"Dimensions('Company')/Hierarchies('Company')/Elements('M5460FAP_')"
		},
		{
			"@id":"Dimensions('Company')/Hierarchies('Company')/Elements('M5460')"
		},
		{
			"@id":"Dimensions('Company')/Hierarchies('Company')/Elements('M5450G')"
		},
		{
			"@id":"Dimensions('Company')/Hierarchies('Company')/Elements('M5450FAP_')"
		},
		{
			"@id":"Dimensions('Company')/Hierarchies('Company')/Elements('M5450')"
		},
		{
			"@id":"Dimensions('Company')/Hierarchies('Company')/Elements('Q.M540GA')"
		},
		{
			"@id":"Dimensions('Company')/Hierarchies('Company')/Elements('M540GA')"
		},
		{
			"@id":"Dimensions('Company')/Hierarchies('Company')/Elements('Q.M5400')"
		},
		{
			"@id":"Dimensions('Company')/Hierarchies('Company')/Elements('M5400FAP_')"
		},
		{
			"@id":"Dimensions('Company')/Hierarchies('Company')/Elements('M5400')"
		},
		{
			"@id":"Dimensions('Company')/Hierarchies('Company')/Elements('M535GA')"
		},
		{
			"@id":"Dimensions('Company')/Hierarchies('Company')/Elements('M5350FAP_')"
		},
		{
			"@id":"Dimensions('Company')/Hierarchies('Company')/Elements('M5350')"
		},
		{
			"@id":"Dimensions('Company')/Hierarchies('Company')/Elements('M534GC')"
		},
		{
			"@id":"Dimensions('Company')/Hierarchies('Company')/Elements('M534GA')"
		},
		{
			"@id":"Dimensions('Company')/Hierarchies('Company')/Elements('M5345FAP_')"
		},
		{
			"@id":"Dimensions('Company')/Hierarchies('Company')/Elements('M5345')"
		},
		{
			"@id":"Dimensions('Company')/Hierarchies('Company')/Elements('M5340FAP_')"
		},
		{
			"@id":"Dimensions('Company')/Hierarchies('Company')/Elements('M5340')"
		},
		{
			"@id":"Dimensions('Company')/Hierarchies('Company')/Elements('M532GA')"
		},
		{
			"@id":"Dimensions('Company')/Hierarchies('Company')/Elements('M5320FAP_')"
		},
		{
			"@id":"Dimensions('Company')/Hierarchies('Company')/Elements('M5320')"
		},
		{
			"@id":"Dimensions('Company')/Hierarchies('Company')/Elements('M531GA')"
		},
		{
			"@id":"Dimensions('Company')/Hierarchies('Company')/Elements('M5310FAP_')"
		},
		{
			"@id":"Dimensions('Company')/Hierarchies('Company')/Elements('M5310')"
		},
		{
			"@id":"Dimensions('Company')/Hierarchies('Company')/Elements('M530GA')"
		},
		{
			"@id":"Dimensions('Company')/Hierarchies('Company')/Elements('M5300FAP_')"
		},
		{
			"@id":"Dimensions('Company')/Hierarchies('Company')/Elements('M5300')"
		},
		{
			"@id":"Dimensions('Company')/Hierarchies('Company')/Elements('Q.M522GA')"
		},
		{
			"@id":"Dimensions('Company')/Hierarchies('Company')/Elements('M522GA')"
		},
		{
			"@id":"Dimensions('Company')/Hierarchies('Company')/Elements('Q.M5220')"
		},
		{
			"@id":"Dimensions('Company')/Hierarchies('Company')/Elements('M5220FAP_')"
		},
		{
			"@id":"Dimensions('Company')/Hierarchies('Company')/Elements('M5220')"
		},
		{
			"@id":"Dimensions('Company')/Hierarchies('Company')/Elements('Q.M521GA')"
		},
		{
			"@id":"Dimensions('Company')/Hierarchies('Company')/Elements('M521GA')"
		},
		{
			"@id":"Dimensions('Company')/Hierarchies('Company')/Elements('Q.M5210')"
		},
		{
			"@id":"Dimensions('Company')/Hierarchies('Company')/Elements('M5210FAP_')"
		},
		{
			"@id":"Dimensions('Company')/Hierarchies('Company')/Elements('M5210')"
		},
		{
			"@id":"Dimensions('Company')/Hierarchies('Company')/Elements('Q.M520GA')"
		},
		{
			"@id":"Dimensions('Company')/Hierarchies('Company')/Elements('M520GA')"
		},
		{
			"@id":"Dimensions('Company')/Hierarchies('Company')/Elements('Q.M5200')"
		},
		{
			"@id":"Dimensions('Company')/Hierarchies('Company')/Elements('M5200FAP_')"
		},
		{
			"@id":"Dimensions('Company')/Hierarchies('Company')/Elements('M5200')"
		},
		{
			"@id":"Dimensions('Company')/Hierarchies('Company')/Elements('M519GA')"
		},
		{
			"@id":"Dimensions('Company')/Hierarchies('Company')/Elements('M5190FAP_')"
		},
		{
			"@id":"Dimensions('Company')/Hierarchies('Company')/Elements('M5190')"
		},
		{
			"@id":"Dimensions('Company')/Hierarchies('Company')/Elements('Q.M518GA')"
		},
		{
			"@id":"Dimensions('Company')/Hierarchies('Company')/Elements('M518GA')"
		},
		{
			"@id":"Dimensions('Company')/Hierarchies('Company')/Elements('Q.M5187')"
		},
		{
			"@id":"Dimensions('Company')/Hierarchies('Company')/Elements('M5187FAP_')"
		},
		{
			"@id":"Dimensions('Company')/Hierarchies('Company')/Elements('M5187')"
		},
		{
			"@id":"Dimensions('Company')/Hierarchies('Company')/Elements('M515GA')"
		},
		{
			"@id":"Dimensions('Company')/Hierarchies('Company')/Elements('M5150FAP_')"
		},
		{
			"@id":"Dimensions('Company')/Hierarchies('Company')/Elements('M5150')"
		},
		{
			"@id":"Dimensions('Company')/Hierarchies('Company')/Elements('M514GC')"
		},
		{
			"@id":"Dimensions('Company')/Hierarchies('Company')/Elements('M514GA')"
		},
		{
			"@id":"Dimensions('Company')/Hierarchies('Company')/Elements('M5146G')"
		},
		{
			"@id":"Dimensions('Company')/Hierarchies('Company')/Elements('M5146FAP_')"
		},
		{
			"@id":"Dimensions('Company')/Hierarchies('Company')/Elements('M5146')"
		},
		{
			"@id":"Dimensions('Company')/Hierarchies('Company')/Elements('M5145FAP_')"
		},
		{
			"@id":"Dimensions('Company')/Hierarchies('Company')/Elements('M5145')"
		},
		{
			"@id":"Dimensions('Company')/Hierarchies('Company')/Elements('Q.M5142G')"
		},
		{
			"@id":"Dimensions('Company')/Hierarchies('Company')/Elements('M5142G')"
		},
		{
			"@id":"Dimensions('Company')/Hierarchies('Company')/Elements('Q.M5142')"
		},
		{
			"@id":"Dimensions('Company')/Hierarchies('Company')/Elements('M5142FAP_')"
		},
		{
			"@id":"Dimensions('Company')/Hierarchies('Company')/Elements('M5142')"
		},
		{
			"@id":"Dimensions('Company')/Hierarchies('Company')/Elements('Q.M5141G')"
		},
		{
			"@id":"Dimensions('Company')/Hierarchies('Company')/Elements('M5141G')"
		},
		{
			"@id":"Dimensions('Company')/Hierarchies('Company')/Elements('Q.M5141')"
		},
		{
			"@id":"Dimensions('Company')/Hierarchies('Company')/Elements('M5141FAP_')"
		},
		{
			"@id":"Dimensions('Company')/Hierarchies('Company')/Elements('M5141')"
		},
		{
			"@id":"Dimensions('Company')/Hierarchies('Company')/Elements('M5140FAP_')"
		},
		{
			"@id":"Dimensions('Company')/Hierarchies('Company')/Elements('M5140')"
		},
		{
			"@id":"Dimensions('Company')/Hierarchies('Company')/Elements('M512GA')"
		},
		{
			"@id":"Dimensions('Company')/Hierarchies('Company')/Elements('M5120FAP_')"
		},
		{
			"@id":"Dimensions('Company')/Hierarchies('Company')/Elements('M5120')"
		},
		{
			"@id":"Dimensions('Company')/Hierarchies('Company')/Elements('M511GA')"
		},
		{
			"@id":"Dimensions('Company')/Hierarchies('Company')/Elements('Q.M511C')"
		},
		{
			"@id":"Dimensions('Company')/Hierarchies('Company')/Elements('M511C')"
		},
		{
			"@id":"Dimensions('Company')/Hierarchies('Company')/Elements('M5115G')"
		},
		{
			"@id":"Dimensions('Company')/Hierarchies('Company')/Elements('M5115FAP_')"
		},
		{
			"@id":"Dimensions('Company')/Hierarchies('Company')/Elements('M5115')"
		},
		{
			"@id":"Dimensions('Company')/Hierarchies('Company')/Elements('M5110FAP_')"
		},
		{
			"@id":"Dimensions('Company')/Hierarchies('Company')/Elements('M5110')"
		},
		{
			"@id":"Dimensions('Company')/Hierarchies('Company')/Elements('M510GA')"
		},
		{
			"@id":"Dimensions('Company')/Hierarchies('Company')/Elements('Q.M5103G')"
		},
		{
			"@id":"Dimensions('Company')/Hierarchies('Company')/Elements('M5103G')"
		},
		{
			"@id":"Dimensions('Company')/Hierarchies('Company')/Elements('Q.M51030')"
		},
		{
			"@id":"Dimensions('Company')/Hierarchies('Company')/Elements('M51030FAP_')"
		},
		{
			"@id":"Dimensions('Company')/Hierarchies('Company')/Elements('M51030')"
		},
		{
			"@id":"Dimensions('Company')/Hierarchies('Company')/Elements('M5100FAP_')"
		},
		{
			"@id":"Dimensions('Company')/Hierarchies('Company')/Elements('M5100')"
		},
		{
			"@id":"Dimensions('Company')/Hierarchies('Company')/Elements('M506GA')"
		},
		{
			"@id":"Dimensions('Company')/Hierarchies('Company')/Elements('M5060FAP_')"
		},
		{
			"@id":"Dimensions('Company')/Hierarchies('Company')/Elements('M5060')"
		},
		{
			"@id":"Dimensions('Company')/Hierarchies('Company')/Elements('M505GA')"
		},
		{
			"@id":"Dimensions('Company')/Hierarchies('Company')/Elements('M5050FAP_')"
		},
		{
			"@id":"Dimensions('Company')/Hierarchies('Company')/Elements('M5050')"
		},
		{
			"@id":"Dimensions('Company')/Hierarchies('Company')/Elements('M502GA')"
		},
		{
			"@id":"Dimensions('Company')/Hierarchies('Company')/Elements('M5020FAP_')"
		},
		{
			"@id":"Dimensions('Company')/Hierarchies('Company')/Elements('M5020')"
		},
		{
			"@id":"Dimensions('Company')/Hierarchies('Company')/Elements('M500GA')"
		},
		{
			"@id":"Dimensions('Company')/Hierarchies('Company')/Elements('M500C')"
		},
		{
			"@id":"Dimensions('Company')/Hierarchies('Company')/Elements('M5000FAP_')"
		},
		{
			"@id":"Dimensions('Company')/Hierarchies('Company')/Elements('M5000')"
		},
		{
			"@id":"Dimensions('Company')/Hierarchies('Company')/Elements('Q.M450GA')"
		},
		{
			"@id":"Dimensions('Company')/Hierarchies('Company')/Elements('M450GA')"
		},
		{
			"@id":"Dimensions('Company')/Hierarchies('Company')/Elements('Q.M4500')"
		},
		{
			"@id":"Dimensions('Company')/Hierarchies('Company')/Elements('M4500FAP_')"
		},
		{
			"@id":"Dimensions('Company')/Hierarchies('Company')/Elements('M4500')"
		},
		{
			"@id":"Dimensions('Company')/Hierarchies('Company')/Elements('M441GA')"
		},
		{
			"@id":"Dimensions('Company')/Hierarchies('Company')/Elements('M4410FAP_')"
		},
		{
			"@id":"Dimensions('Company')/Hierarchies('Company')/Elements('M4410')"
		},
		{
			"@id":"Dimensions('Company')/Hierarchies('Company')/Elements('M440GA')"
		},
		{
			"@id":"Dimensions('Company')/Hierarchies('Company')/Elements('M4400FAP_')"
		},
		{
			"@id":"Dimensions('Company')/Hierarchies('Company')/Elements('M4400')"
		},
		{
			"@id":"Dimensions('Company')/Hierarchies('Company')/Elements('M4370G')"
		},
		{
			"@id":"Dimensions('Company')/Hierarchies('Company')/Elements('M4370FAP_')"
		},
		{
			"@id":"Dimensions('Company')/Hierarchies('Company')/Elements('M4370')"
		},
		{
			"@id":"Dimensions('Company')/Hierarchies('Company')/Elements('M4360G')"
		},
		{
			"@id":"Dimensions('Company')/Hierarchies('Company')/Elements('M4360FAP_')"
		},
		{
			"@id":"Dimensions('Company')/Hierarchies('Company')/Elements('M4360')"
		},
		{
			"@id":"Dimensions('Company')/Hierarchies('Company')/Elements('M435GA')"
		},
		{
			"@id":"Dimensions('Company')/Hierarchies('Company')/Elements('M4355G')"
		},
		{
			"@id":"Dimensions('Company')/Hierarchies('Company')/Elements('M4355FAP_')"
		},
		{
			"@id":"Dimensions('Company')/Hierarchies('Company')/Elements('M4355')"
		},
		{
			"@id":"Dimensions('Company')/Hierarchies('Company')/Elements('M4350FAP_')"
		},
		{
			"@id":"Dimensions('Company')/Hierarchies('Company')/Elements('M4350')"
		},
		{
			"@id":"Dimensions('Company')/Hierarchies('Company')/Elements('M430GA')"
		},
		{
			"@id":"Dimensions('Company')/Hierarchies('Company')/Elements('M4300FAP_')"
		},
		{
			"@id":"Dimensions('Company')/Hierarchies('Company')/Elements('M4300')"
		},
		{
			"@id":"Dimensions('Company')/Hierarchies('Company')/Elements('M422GA')"
		},
		{
			"@id":"Dimensions('Company')/Hierarchies('Company')/Elements('M4220FAP_')"
		},
		{
			"@id":"Dimensions('Company')/Hierarchies('Company')/Elements('M4220')"
		},
		{
			"@id":"Dimensions('Company')/Hierarchies('Company')/Elements('M421GA')"
		},
		{
			"@id":"Dimensions('Company')/Hierarchies('Company')/Elements('M4210FAP_')"
		},
		{
			"@id":"Dimensions('Company')/Hierarchies('Company')/Elements('M4210')"
		},
		{
			"@id":"Dimensions('Company')/Hierarchies('Company')/Elements('M420GC')"
		},
		{
			"@id":"Dimensions('Company')/Hierarchies('Company')/Elements('M420GA')"
		},
		{
			"@id":"Dimensions('Company')/Hierarchies('Company')/Elements('M4205FAP_')"
		},
		{
			"@id":"Dimensions('Company')/Hierarchies('Company')/Elements('M4205')"
		},
		{
			"@id":"Dimensions('Company')/Hierarchies('Company')/Elements('M4200FAP_')"
		},
		{
			"@id":"Dimensions('Company')/Hierarchies('Company')/Elements('M4200')"
		},
		{
			"@id":"Dimensions('Company')/Hierarchies('Company')/Elements('M415GA')"
		},
		{
			"@id":"Dimensions('Company')/Hierarchies('Company')/Elements('M4150FAP_')"
		},
		{
			"@id":"Dimensions('Company')/Hierarchies('Company')/Elements('M4150')"
		},
		{
			"@id":"Dimensions('Company')/Hierarchies('Company')/Elements('M412GA')"
		},
		{
			"@id":"Dimensions('Company')/Hierarchies('Company')/Elements('M4120FAP_')"
		},
		{
			"@id":"Dimensions('Company')/Hierarchies('Company')/Elements('M4120')"
		},
		{
			"@id":"Dimensions('Company')/Hierarchies('Company')/Elements('M411GA')"
		},
		{
			"@id":"Dimensions('Company')/Hierarchies('Company')/Elements('M4110FAP_')"
		},
		{
			"@id":"Dimensions('Company')/Hierarchies('Company')/Elements('M4110')"
		},
		{
			"@id":"Dimensions('Company')/Hierarchies('Company')/Elements('M410GA')"
		},
		{
			"@id":"Dimensions('Company')/Hierarchies('Company')/Elements('M4100FAP_')"
		},
		{
			"@id":"Dimensions('Company')/Hierarchies('Company')/Elements('M4100')"
		},
		{
			"@id":"Dimensions('Company')/Hierarchies('Company')/Elements('M400GA')"
		},
		{
			"@id":"Dimensions('Company')/Hierarchies('Company')/Elements('M400C')"
		},
		{
			"@id":"Dimensions('Company')/Hierarchies('Company')/Elements('M4000FAP_')"
		},
		{
			"@id":"Dimensions('Company')/Hierarchies('Company')/Elements('M4000')"
		},
		{
			"@id":"Dimensions('Company')/Hierarchies('Company')/Elements('M300GA')"
		},
		{
			"@id":"Dimensions('Company')/Hierarchies('Company')/Elements('M3000FAP_')"
		},
		{
			"@id":"Dimensions('Company')/Hierarchies('Company')/Elements('M3000')"
		},
		{
			"@id":"Dimensions('Company')/Hierarchies('Company')/Elements('M240GA')"
		},
		{
			"@id":"Dimensions('Company')/Hierarchies('Company')/Elements('M2400FAP_')"
		},
		{
			"@id":"Dimensions('Company')/Hierarchies('Company')/Elements('M2400')"
		},
		{
			"@id":"Dimensions('Company')/Hierarchies('Company')/Elements('M230GA')"
		},
		{
			"@id":"Dimensions('Company')/Hierarchies('Company')/Elements('M2300FAP_')"
		},
		{
			"@id":"Dimensions('Company')/Hierarchies('Company')/Elements('M2300')"
		},
		{
			"@id":"Dimensions('Company')/Hierarchies('Company')/Elements('M220GA')"
		},
		{
			"@id":"Dimensions('Company')/Hierarchies('Company')/Elements('M2200FAP_')"
		},
		{
			"@id":"Dimensions('Company')/Hierarchies('Company')/Elements('M2200')"
		},
		{
			"@id":"Dimensions('Company')/Hierarchies('Company')/Elements('M210GA')"
		},
		{
			"@id":"Dimensions('Company')/Hierarchies('Company')/Elements('M2100FAP_')"
		},
		{
			"@id":"Dimensions('Company')/Hierarchies('Company')/Elements('M2100')"
		},
		{
			"@id":"Dimensions('Company')/Hierarchies('Company')/Elements('M200GA')"
		},
		{
			"@id":"Dimensions('Company')/Hierarchies('Company')/Elements('M200C')"
		},
		{
			"@id":"Dimensions('Company')/Hierarchies('Company')/Elements('M2000FAP_')"
		},
		{
			"@id":"Dimensions('Company')/Hierarchies('Company')/Elements('M2000')"
		},
		{
			"@id":"Dimensions('Company')/Hierarchies('Company')/Elements('M100GA')"
		},
		{
			"@id":"Dimensions('Company')/Hierarchies('Company')/Elements('M1000FAP_')"
		},
		{
			"@id":"Dimensions('Company')/Hierarchies('Company')/Elements('M1000')"
		},
		{
			"@id":"Dimensions('Company')/Hierarchies('Company')/Elements('L900GA')"
		},
		{
			"@id":"Dimensions('Company')/Hierarchies('Company')/Elements('L9001G')"
		},
		{
			"@id":"Dimensions('Company')/Hierarchies('Company')/Elements('L9001')"
		},
		{
			"@id":"Dimensions('Company')/Hierarchies('Company')/Elements('L9000')"
		},
		{
			"@id":"Dimensions('Company')/Hierarchies('Company')/Elements('L6403G')"
		},
		{
			"@id":"Dimensions('Company')/Hierarchies('Company')/Elements('L64030')"
		},
		{
			"@id":"Dimensions('Company')/Hierarchies('Company')/Elements('L630GA')"
		},
		{
			"@id":"Dimensions('Company')/Hierarchies('Company')/Elements('L6303G')"
		},
		{
			"@id":"Dimensions('Company')/Hierarchies('Company')/Elements('L6303')"
		},
		{
			"@id":"Dimensions('Company')/Hierarchies('Company')/Elements('L6300')"
		},
		{
			"@id":"Dimensions('Company')/Hierarchies('Company')/Elements('L621GA')"
		},
		{
			"@id":"Dimensions('Company')/Hierarchies('Company')/Elements('L6215G')"
		},
		{
			"@id":"Dimensions('Company')/Hierarchies('Company')/Elements('L620GA')"
		},
		{
			"@id":"Dimensions('Company')/Hierarchies('Company')/Elements('L6201C')"
		},
		{
			"@id":"Dimensions('Company')/Hierarchies('Company')/Elements('L62015')"
		},
		{
			"@id":"Dimensions('Company')/Hierarchies('Company')/Elements('L6201')"
		},
		{
			"@id":"Dimensions('Company')/Hierarchies('Company')/Elements('L6200')"
		},
		{
			"@id":"Dimensions('Company')/Hierarchies('Company')/Elements('L611GA')"
		},
		{
			"@id":"Dimensions('Company')/Hierarchies('Company')/Elements('L610GA')"
		},
		{
			"@id":"Dimensions('Company')/Hierarchies('Company')/Elements('L6103G')"
		},
		{
			"@id":"Dimensions('Company')/Hierarchies('Company')/Elements('L61030')"
		},
		{
			"@id":"Dimensions('Company')/Hierarchies('Company')/Elements('L6101C')"
		},
		{
			"@id":"Dimensions('Company')/Hierarchies('Company')/Elements('L6101')"
		},
		{
			"@id":"Dimensions('Company')/Hierarchies('Company')/Elements('L6100')"
		},
		{
			"@id":"Dimensions('Company')/Hierarchies('Company')/Elements('L601GA')"
		},
		{
			"@id":"Dimensions('Company')/Hierarchies('Company')/Elements('L600GA')"
		},
		{
			"@id":"Dimensions('Company')/Hierarchies('Company')/Elements('L6005G')"
		},
		{
			"@id":"Dimensions('Company')/Hierarchies('Company')/Elements('L60050')"
		},
		{
			"@id":"Dimensions('Company')/Hierarchies('Company')/Elements('L6001')"
		},
		{
			"@id":"Dimensions('Company')/Hierarchies('Company')/Elements('L6000')"
		},
		{
			"@id":"Dimensions('Company')/Hierarchies('Company')/Elements('L5801G')"
		},
		{
			"@id":"Dimensions('Company')/Hierarchies('Company')/Elements('L5801')"
		},
		{
			"@id":"Dimensions('Company')/Hierarchies('Company')/Elements('L5800')"
		},
		{
			"@id":"Dimensions('Company')/Hierarchies('Company')/Elements('L570GA')"
		},
		{
			"@id":"Dimensions('Company')/Hierarchies('Company')/Elements('L5700')"
		},
		{
			"@id":"Dimensions('Company')/Hierarchies('Company')/Elements('L5604G')"
		},
		{
			"@id":"Dimensions('Company')/Hierarchies('Company')/Elements('L56040')"
		},
		{
			"@id":"Dimensions('Company')/Hierarchies('Company')/Elements('L5602G')"
		},
		{
			"@id":"Dimensions('Company')/Hierarchies('Company')/Elements('L56020')"
		},
		{
			"@id":"Dimensions('Company')/Hierarchies('Company')/Elements('L5601G')"
		},
		{
			"@id":"Dimensions('Company')/Hierarchies('Company')/Elements('L56010')"
		},
		{
			"@id":"Dimensions('Company')/Hierarchies('Company')/Elements('L5600')"
		},
		{
			"@id":"Dimensions('Company')/Hierarchies('Company')/Elements('L5552G')"
		},
		{
			"@id":"Dimensions('Company')/Hierarchies('Company')/Elements('L5551G')"
		},
		{
			"@id":"Dimensions('Company')/Hierarchies('Company')/Elements('L55511')"
		},
		{
			"@id":"Dimensions('Company')/Hierarchies('Company')/Elements('L55510')"
		},
		{
			"@id":"Dimensions('Company')/Hierarchies('Company')/Elements('L553GA')"
		},
		{
			"@id":"Dimensions('Company')/Hierarchies('Company')/Elements('L552GA')"
		},
		{
			"@id":"Dimensions('Company')/Hierarchies('Company')/Elements('L552C')"
		},
		{
			"@id":"Dimensions('Company')/Hierarchies('Company')/Elements('L545GA')"
		},
		{
			"@id":"Dimensions('Company')/Hierarchies('Company')/Elements('L5454G')"
		},
		{
			"@id":"Dimensions('Company')/Hierarchies('Company')/Elements('L5453G')"
		},
		{
			"@id":"Dimensions('Company')/Hierarchies('Company')/Elements('L5452G')"
		},
		{
			"@id":"Dimensions('Company')/Hierarchies('Company')/Elements('L5451G')"
		},
		{
			"@id":"Dimensions('Company')/Hierarchies('Company')/Elements('L54514')"
		},
		{
			"@id":"Dimensions('Company')/Hierarchies('Company')/Elements('L54513')"
		},
		{
			"@id":"Dimensions('Company')/Hierarchies('Company')/Elements('L54512')"
		},
		{
			"@id":"Dimensions('Company')/Hierarchies('Company')/Elements('L54511')"
		},
		{
			"@id":"Dimensions('Company')/Hierarchies('Company')/Elements('L54510')"
		},
		{
			"@id":"Dimensions('Company')/Hierarchies('Company')/Elements('L542GA')"
		},
		{
			"@id":"Dimensions('Company')/Hierarchies('Company')/Elements('Q.L541GA')"
		},
		{
			"@id":"Dimensions('Company')/Hierarchies('Company')/Elements('L541GA')"
		},
		{
			"@id":"Dimensions('Company')/Hierarchies('Company')/Elements('L540GA')"
		},
		{
			"@id":"Dimensions('Company')/Hierarchies('Company')/Elements('L5402C')"
		},
		{
			"@id":"Dimensions('Company')/Hierarchies('Company')/Elements('L5402')"
		},
		{
			"@id":"Dimensions('Company')/Hierarchies('Company')/Elements('Q.L5401')"
		},
		{
			"@id":"Dimensions('Company')/Hierarchies('Company')/Elements('L5401')"
		},
		{
			"@id":"Dimensions('Company')/Hierarchies('Company')/Elements('L5400')"
		},
		{
			"@id":"Dimensions('Company')/Hierarchies('Company')/Elements('L531GA')"
		},
		{
			"@id":"Dimensions('Company')/Hierarchies('Company')/Elements('L5310')"
		},
		{
			"@id":"Dimensions('Company')/Hierarchies('Company')/Elements('L530GA')"
		},
		{
			"@id":"Dimensions('Company')/Hierarchies('Company')/Elements('L5300')"
		},
		{
			"@id":"Dimensions('Company')/Hierarchies('Company')/Elements('L526GA')"
		},
		{
			"@id":"Dimensions('Company')/Hierarchies('Company')/Elements('L524GA')"
		},
		{
			"@id":"Dimensions('Company')/Hierarchies('Company')/Elements('L522GA')"
		},
		{
			"@id":"Dimensions('Company')/Hierarchies('Company')/Elements('L521GA')"
		},
		{
			"@id":"Dimensions('Company')/Hierarchies('Company')/Elements('L5210')"
		},
		{
			"@id":"Dimensions('Company')/Hierarchies('Company')/Elements('L520GA')"
		},
		{
			"@id":"Dimensions('Company')/Hierarchies('Company')/Elements('L52060')"
		},
		{
			"@id":"Dimensions('Company')/Hierarchies('Company')/Elements('L5204')"
		},
		{
			"@id":"Dimensions('Company')/Hierarchies('Company')/Elements('L5203G')"
		},
		{
			"@id":"Dimensions('Company')/Hierarchies('Company')/Elements('L52030')"
		},
		{
			"@id":"Dimensions('Company')/Hierarchies('Company')/Elements('L5202C')"
		},
		{
			"@id":"Dimensions('Company')/Hierarchies('Company')/Elements('L5202')"
		},
		{
			"@id":"Dimensions('Company')/Hierarchies('Company')/Elements('L5200')"
		},
		{
			"@id":"Dimensions('Company')/Hierarchies('Company')/Elements('L5193G')"
		},
		{
			"@id":"Dimensions('Company')/Hierarchies('Company')/Elements('L5190')"
		},
		{
			"@id":"Dimensions('Company')/Hierarchies('Company')/Elements('L515GA')"
		},
		{
			"@id":"Dimensions('Company')/Hierarchies('Company')/Elements('L5153C')"
		},
		{
			"@id":"Dimensions('Company')/Hierarchies('Company')/Elements('L5153')"
		},
		{
			"@id":"Dimensions('Company')/Hierarchies('Company')/Elements('L5152')"
		},
		{
			"@id":"Dimensions('Company')/Hierarchies('Company')/Elements('L5150')"
		},
		{
			"@id":"Dimensions('Company')/Hierarchies('Company')/Elements('L514GA')"
		},
		{
			"@id":"Dimensions('Company')/Hierarchies('Company')/Elements('L514G')"
		},
		{
			"@id":"Dimensions('Company')/Hierarchies('Company')/Elements('L5142G')"
		},
		{
			"@id":"Dimensions('Company')/Hierarchies('Company')/Elements('L5142')"
		},
		{
			"@id":"Dimensions('Company')/Hierarchies('Company')/Elements('L5141G')"
		},
		{
			"@id":"Dimensions('Company')/Hierarchies('Company')/Elements('L51414')"
		},
		{
			"@id":"Dimensions('Company')/Hierarchies('Company')/Elements('L5141')"
		},
		{
			"@id":"Dimensions('Company')/Hierarchies('Company')/Elements('L5140')"
		},
		{
			"@id":"Dimensions('Company')/Hierarchies('Company')/Elements('L512GA')"
		},
		{
			"@id":"Dimensions('Company')/Hierarchies('Company')/Elements('L5124G')"
		},
		{
			"@id":"Dimensions('Company')/Hierarchies('Company')/Elements('L5124C')"
		},
		{
			"@id":"Dimensions('Company')/Hierarchies('Company')/Elements('L5124')"
		},
		{
			"@id":"Dimensions('Company')/Hierarchies('Company')/Elements('L5122G')"
		},
		{
			"@id":"Dimensions('Company')/Hierarchies('Company')/Elements('L5122C')"
		},
		{
			"@id":"Dimensions('Company')/Hierarchies('Company')/Elements('L5122')"
		},
		{
			"@id":"Dimensions('Company')/Hierarchies('Company')/Elements('L5121G')"
		},
		{
			"@id":"Dimensions('Company')/Hierarchies('Company')/Elements('L5121C')"
		},
		{
			"@id":"Dimensions('Company')/Hierarchies('Company')/Elements('L5121')"
		},
		{
			"@id":"Dimensions('Company')/Hierarchies('Company')/Elements('L5120')"
		},
		{
			"@id":"Dimensions('Company')/Hierarchies('Company')/Elements('L511GA')"
		},
		{
			"@id":"Dimensions('Company')/Hierarchies('Company')/Elements('L510GA')"
		},
		{
			"@id":"Dimensions('Company')/Hierarchies('Company')/Elements('L5103G')"
		},
		{
			"@id":"Dimensions('Company')/Hierarchies('Company')/Elements('L51030')"
		},
		{
			"@id":"Dimensions('Company')/Hierarchies('Company')/Elements('L5101')"
		},
		{
			"@id":"Dimensions('Company')/Hierarchies('Company')/Elements('L5100')"
		},
		{
			"@id":"Dimensions('Company')/Hierarchies('Company')/Elements('L507GA')"
		},
		{
			"@id":"Dimensions('Company')/Hierarchies('Company')/Elements('L5070C')"
		},
		{
			"@id":"Dimensions('Company')/Hierarchies('Company')/Elements('L5070')"
		},
		{
			"@id":"Dimensions('Company')/Hierarchies('Company')/Elements('L5068G')"
		},
		{
			"@id":"Dimensions('Company')/Hierarchies('Company')/Elements('L504GA')"
		},
		{
			"@id":"Dimensions('Company')/Hierarchies('Company')/Elements('L5031G')"
		},
		{
			"@id":"Dimensions('Company')/Hierarchies('Company')/Elements('L500GA')"
		},
		{
			"@id":"Dimensions('Company')/Hierarchies('Company')/Elements('L50068')"
		},
		{
			"@id":"Dimensions('Company')/Hierarchies('Company')/Elements('L5004C')"
		},
		{
			"@id":"Dimensions('Company')/Hierarchies('Company')/Elements('L5004')"
		},
		{
			"@id":"Dimensions('Company')/Hierarchies('Company')/Elements('L50031')"
		},
		{
			"@id":"Dimensions('Company')/Hierarchies('Company')/Elements('L5000')"
		},
		{
			"@id":"Dimensions('Company')/Hierarchies('Company')/Elements('L498GA')"
		},
		{
			"@id":"Dimensions('Company')/Hierarchies('Company')/Elements('L4500')"
		},
		{
			"@id":"Dimensions('Company')/Hierarchies('Company')/Elements('L442GA')"
		},
		{
			"@id":"Dimensions('Company')/Hierarchies('Company')/Elements('L4420')"
		},
		{
			"@id":"Dimensions('Company')/Hierarchies('Company')/Elements('L441GA')"
		},
		{
			"@id":"Dimensions('Company')/Hierarchies('Company')/Elements('L4411')"
		},
		{
			"@id":"Dimensions('Company')/Hierarchies('Company')/Elements('L4410C')"
		},
		{
			"@id":"Dimensions('Company')/Hierarchies('Company')/Elements('L4410')"
		},
		{
			"@id":"Dimensions('Company')/Hierarchies('Company')/Elements('L440GA')"
		},
		{
			"@id":"Dimensions('Company')/Hierarchies('Company')/Elements('L4400')"
		},
		{
			"@id":"Dimensions('Company')/Hierarchies('Company')/Elements('L4370G')"
		},
		{
			"@id":"Dimensions('Company')/Hierarchies('Company')/Elements('L43700')"
		},
		{
			"@id":"Dimensions('Company')/Hierarchies('Company')/Elements('L433GA')"
		},
		{
			"@id":"Dimensions('Company')/Hierarchies('Company')/Elements('L432GA')"
		},
		{
			"@id":"Dimensions('Company')/Hierarchies('Company')/Elements('L432C')"
		},
		{
			"@id":"Dimensions('Company')/Hierarchies('Company')/Elements('L430GA')"
		},
		{
			"@id":"Dimensions('Company')/Hierarchies('Company')/Elements('L4304G')"
		},
		{
			"@id":"Dimensions('Company')/Hierarchies('Company')/Elements('L43040')"
		},
		{
			"@id":"Dimensions('Company')/Hierarchies('Company')/Elements('L4303')"
		},
		{
			"@id":"Dimensions('Company')/Hierarchies('Company')/Elements('L4302')"
		},
		{
			"@id":"Dimensions('Company')/Hierarchies('Company')/Elements('L4301G')"
		},
		{
			"@id":"Dimensions('Company')/Hierarchies('Company')/Elements('L43010')"
		},
		{
			"@id":"Dimensions('Company')/Hierarchies('Company')/Elements('L4300')"
		},
		{
			"@id":"Dimensions('Company')/Hierarchies('Company')/Elements('L422GA')"
		},
		{
			"@id":"Dimensions('Company')/Hierarchies('Company')/Elements('L4222G')"
		},
		{
			"@id":"Dimensions('Company')/Hierarchies('Company')/Elements('L4222')"
		},
		{
			"@id":"Dimensions('Company')/Hierarchies('Company')/Elements('L4221G')"
		},
		{
			"@id":"Dimensions('Company')/Hierarchies('Company')/Elements('L4221')"
		},
		{
			"@id":"Dimensions('Company')/Hierarchies('Company')/Elements('L4220')"
		},
		{
			"@id":"Dimensions('Company')/Hierarchies('Company')/Elements('L421GA')"
		},
		{
			"@id":"Dimensions('Company')/Hierarchies('Company')/Elements('L4211C')"
		},
		{
			"@id":"Dimensions('Company')/Hierarchies('Company')/Elements('L4211')"
		},
		{
			"@id":"Dimensions('Company')/Hierarchies('Company')/Elements('L4210')"
		},
		{
			"@id":"Dimensions('Company')/Hierarchies('Company')/Elements('L420GA')"
		},
		{
			"@id":"Dimensions('Company')/Hierarchies('Company')/Elements('L4200')"
		},
		{
			"@id":"Dimensions('Company')/Hierarchies('Company')/Elements('L410GA')"
		},
		{
			"@id":"Dimensions('Company')/Hierarchies('Company')/Elements('L4100')"
		},
		{
			"@id":"Dimensions('Company')/Hierarchies('Company')/Elements('L400GA')"
		},
		{
			"@id":"Dimensions('Company')/Hierarchies('Company')/Elements('L4000')"
		},
		{
			"@id":"Dimensions('Company')/Hierarchies('Company')/Elements('L212GA')"
		},
		{
			"@id":"Dimensions('Company')/Hierarchies('Company')/Elements('L210GA')"
		},
		{
			"@id":"Dimensions('Company')/Hierarchies('Company')/Elements('L2105C')"
		},
		{
			"@id":"Dimensions('Company')/Hierarchies('Company')/Elements('L2105')"
		},
		{
			"@id":"Dimensions('Company')/Hierarchies('Company')/Elements('L2104C')"
		},
		{
			"@id":"Dimensions('Company')/Hierarchies('Company')/Elements('L2104')"
		},
		{
			"@id":"Dimensions('Company')/Hierarchies('Company')/Elements('L2102')"
		},
		{
			"@id":"Dimensions('Company')/Hierarchies('Company')/Elements('L2100')"
		},
		{
			"@id":"Dimensions('Company')/Hierarchies('Company')/Elements('L205GA')"
		},
		{
			"@id":"Dimensions('Company')/Hierarchies('Company')/Elements('L204GA')"
		},
		{
			"@id":"Dimensions('Company')/Hierarchies('Company')/Elements('L203GA')"
		},
		{
			"@id":"Dimensions('Company')/Hierarchies('Company')/Elements('L2030')"
		},
		{
			"@id":"Dimensions('Company')/Hierarchies('Company')/Elements('L202GA')"
		},
		{
			"@id":"Dimensions('Company')/Hierarchies('Company')/Elements('L2020')"
		},
		{
			"@id":"Dimensions('Company')/Hierarchies('Company')/Elements('L201GA')"
		},
		{
			"@id":"Dimensions('Company')/Hierarchies('Company')/Elements('L2010C')"
		},
		{
			"@id":"Dimensions('Company')/Hierarchies('Company')/Elements('L2010')"
		},
		{
			"@id":"Dimensions('Company')/Hierarchies('Company')/Elements('L200GA')"
		},
		{
			"@id":"Dimensions('Company')/Hierarchies('Company')/Elements('L2000')"
		},
		{
			"@id":"Dimensions('Company')/Hierarchies('Company')/Elements('L1070G')"
		},
		{
			"@id":"Dimensions('Company')/Hierarchies('Company')/Elements('L1070')"
		},
		{
			"@id":"Dimensions('Company')/Hierarchies('Company')/Elements('L106GA')"
		},
		{
			"@id":"Dimensions('Company')/Hierarchies('Company')/Elements('L1060C')"
		},
		{
			"@id":"Dimensions('Company')/Hierarchies('Company')/Elements('L1060')"
		},
		{
			"@id":"Dimensions('Company')/Hierarchies('Company')/Elements('L105GA')"
		},
		{
			"@id":"Dimensions('Company')/Hierarchies('Company')/Elements('L1050')"
		},
		{
			"@id":"Dimensions('Company')/Hierarchies('Company')/Elements('L101GA')"
		},
		{
			"@id":"Dimensions('Company')/Hierarchies('Company')/Elements('L1010C')"
		},
		{
			"@id":"Dimensions('Company')/Hierarchies('Company')/Elements('L1010')"
		},
		{
			"@id":"Dimensions('Company')/Hierarchies('Company')/Elements('L100GA')"
		},
		{
			"@id":"Dimensions('Company')/Hierarchies('Company')/Elements('L1001G')"
		},
		{
			"@id":"Dimensions('Company')/Hierarchies('Company')/Elements('L1001C')"
		},
		{
			"@id":"Dimensions('Company')/Hierarchies('Company')/Elements('L1001')"
		},
		{
			"@id":"Dimensions('Company')/Hierarchies('Company')/Elements('L1000')"
		},
		{
			"@id":"Dimensions('Company')/Hierarchies('Company')/Elements('Q.JMSRET')"
		},
		{
			"@id":"Dimensions('Company')/Hierarchies('Company')/Elements('JMSRET')"
		},
		{
			"@id":"Dimensions('Company')/Hierarchies('Company')/Elements('Q.JMSCOT')"
		},
		{
			"@id":"Dimensions('Company')/Hierarchies('Company')/Elements('JMSCOT')"
		},
		{
			"@id":"Dimensions('Company')/Hierarchies('Company')/Elements('Q.JMSBOT')"
		},
		{
			"@id":"Dimensions('Company')/Hierarchies('Company')/Elements('JMSBOT')"
		},
		{
			"@id":"Dimensions('Company')/Hierarchies('Company')/Elements('Q.HUGHTA')"
		},
		{
			"@id":"Dimensions('Company')/Hierarchies('Company')/Elements('HUGHTA')"
		},
		{
			"@id":"Dimensions('Company')/Hierarchies('Company')/Elements('F62010')"
		},
		{
			"@id":"Dimensions('Company')/Hierarchies('Company')/Elements('F60050')"
		},
		{
			"@id":"Dimensions('Company')/Hierarchies('Company')/Elements('F60020')"
		},
		{
			"@id":"Dimensions('Company')/Hierarchies('Company')/Elements('F58510')"
		},
		{
			"@id":"Dimensions('Company')/Hierarchies('Company')/Elements('F57140')"
		},
		{
			"@id":"Dimensions('Company')/Hierarchies('Company')/Elements('F57110')"
		},
		{
			"@id":"Dimensions('Company')/Hierarchies('Company')/Elements('F54510')"
		},
		{
			"@id":"Dimensions('Company')/Hierarchies('Company')/Elements('Q.F52030')"
		},
		{
			"@id":"Dimensions('Company')/Hierarchies('Company')/Elements('F52030')"
		},
		{
			"@id":"Dimensions('Company')/Hierarchies('Company')/Elements('Q.F52020')"
		},
		{
			"@id":"Dimensions('Company')/Hierarchies('Company')/Elements('F52020')"
		},
		{
			"@id":"Dimensions('Company')/Hierarchies('Company')/Elements('Q.F51540')"
		},
		{
			"@id":"Dimensions('Company')/Hierarchies('Company')/Elements('F51540')"
		},
		{
			"@id":"Dimensions('Company')/Hierarchies('Company')/Elements('F51401')"
		},
		{
			"@id":"Dimensions('Company')/Hierarchies('Company')/Elements('F44100')"
		},
		{
			"@id":"Dimensions('Company')/Hierarchies('Company')/Elements('F43010')"
		},
		{
			"@id":"Dimensions('Company')/Hierarchies('Company')/Elements('F42110')"
		},
		{
			"@id":"Dimensions('Company')/Hierarchies('Company')/Elements('F41010')"
		},
		{
			"@id":"Dimensions('Company')/Hierarchies('Company')/Elements('F21160')"
		},
		{
			"@id":"Dimensions('Company')/Hierarchies('Company')/Elements('F21020')"
		},
		{
			"@id":"Dimensions('Company')/Hierarchies('Company')/Elements('99999')"
		},
		{
			"@id":"Dimensions('Company')/Hierarchies('Company')/Elements('99998')"
		},
		{
			"@id":"Dimensions('Company')/Hierarchies('Company')/Elements('Q.64030')"
		},
		{
			"@id":"Dimensions('Company')/Hierarchies('Company')/Elements('64030')"
		},
		{
			"@id":"Dimensions('Company')/Hierarchies('Company')/Elements('Q.64020')"
		},
		{
			"@id":"Dimensions('Company')/Hierarchies('Company')/Elements('64020')"
		},
		{
			"@id":"Dimensions('Company')/Hierarchies('Company')/Elements('64010')"
		},
		{
			"@id":"Dimensions('Company')/Hierarchies('Company')/Elements('Q.63040')"
		},
		{
			"@id":"Dimensions('Company')/Hierarchies('Company')/Elements('63040')"
		},
		{
			"@id":"Dimensions('Company')/Hierarchies('Company')/Elements('Q.63030')"
		},
		{
			"@id":"Dimensions('Company')/Hierarchies('Company')/Elements('63030')"
		},
		{
			"@id":"Dimensions('Company')/Hierarchies('Company')/Elements('Q.63020')"
		},
		{
			"@id":"Dimensions('Company')/Hierarchies('Company')/Elements('63020')"
		},
		{
			"@id":"Dimensions('Company')/Hierarchies('Company')/Elements('63010')"
		},
		{
			"@id":"Dimensions('Company')/Hierarchies('Company')/Elements('Q.62050')"
		},
		{
			"@id":"Dimensions('Company')/Hierarchies('Company')/Elements('62050')"
		},
		{
			"@id":"Dimensions('Company')/Hierarchies('Company')/Elements('6204P')"
		},
		{
			"@id":"Dimensions('Company')/Hierarchies('Company')/Elements('Q.62040')"
		},
		{
			"@id":"Dimensions('Company')/Hierarchies('Company')/Elements('62040')"
		},
		{
			"@id":"Dimensions('Company')/Hierarchies('Company')/Elements('6203P')"
		},
		{
			"@id":"Dimensions('Company')/Hierarchies('Company')/Elements('62030')"
		},
		{
			"@id":"Dimensions('Company')/Hierarchies('Company')/Elements('6202P')"
		},
		{
			"@id":"Dimensions('Company')/Hierarchies('Company')/Elements('62020')"
		},
		{
			"@id":"Dimensions('Company')/Hierarchies('Company')/Elements('6201P')"
		},
		{
			"@id":"Dimensions('Company')/Hierarchies('Company')/Elements('62019')"
		},
		{
			"@id":"Dimensions('Company')/Hierarchies('Company')/Elements('62015')"
		},
		{
			"@id":"Dimensions('Company')/Hierarchies('Company')/Elements('62010')"
		},
		{
			"@id":"Dimensions('Company')/Hierarchies('Company')/Elements('Q.61099')"
		},
		{
			"@id":"Dimensions('Company')/Hierarchies('Company')/Elements('61099')"
		},
		{
			"@id":"Dimensions('Company')/Hierarchies('Company')/Elements('61090')"
		},
		{
			"@id":"Dimensions('Company')/Hierarchies('Company')/Elements('61080')"
		},
		{
			"@id":"Dimensions('Company')/Hierarchies('Company')/Elements('61070')"
		},
		{
			"@id":"Dimensions('Company')/Hierarchies('Company')/Elements('61065')"
		},
		{
			"@id":"Dimensions('Company')/Hierarchies('Company')/Elements('61060')"
		},
		{
			"@id":"Dimensions('Company')/Hierarchies('Company')/Elements('61053')"
		},
		{
			"@id":"Dimensions('Company')/Hierarchies('Company')/Elements('61051')"
		},
		{
			"@id":"Dimensions('Company')/Hierarchies('Company')/Elements('Q.61050')"
		},
		{
			"@id":"Dimensions('Company')/Hierarchies('Company')/Elements('61050')"
		},
		{
			"@id":"Dimensions('Company')/Hierarchies('Company')/Elements('Q.61040')"
		},
		{
			"@id":"Dimensions('Company')/Hierarchies('Company')/Elements('61040')"
		},
		{
			"@id":"Dimensions('Company')/Hierarchies('Company')/Elements('Q.61030')"
		},
		{
			"@id":"Dimensions('Company')/Hierarchies('Company')/Elements('61030')"
		},
		{
			"@id":"Dimensions('Company')/Hierarchies('Company')/Elements('61020')"
		},
		{
			"@id":"Dimensions('Company')/Hierarchies('Company')/Elements('Q.61010')"
		},
		{
			"@id":"Dimensions('Company')/Hierarchies('Company')/Elements('61010')"
		},
		{
			"@id":"Dimensions('Company')/Hierarchies('Company')/Elements('Q.60051')"
		},
		{
			"@id":"Dimensions('Company')/Hierarchies('Company')/Elements('60051')"
		},
		{
			"@id":"Dimensions('Company')/Hierarchies('Company')/Elements('Q.60050')"
		},
		{
			"@id":"Dimensions('Company')/Hierarchies('Company')/Elements('60050')"
		},
		{
			"@id":"Dimensions('Company')/Hierarchies('Company')/Elements('60040')"
		},
		{
			"@id":"Dimensions('Company')/Hierarchies('Company')/Elements('Q.60030')"
		},
		{
			"@id":"Dimensions('Company')/Hierarchies('Company')/Elements('60030')"
		},
		{
			"@id":"Dimensions('Company')/Hierarchies('Company')/Elements('Q.60020')"
		},
		{
			"@id":"Dimensions('Company')/Hierarchies('Company')/Elements('60020')"
		},
		{
			"@id":"Dimensions('Company')/Hierarchies('Company')/Elements('Q.60010')"
		},
		{
			"@id":"Dimensions('Company')/Hierarchies('Company')/Elements('60010')"
		},
		{
			"@id":"Dimensions('Company')/Hierarchies('Company')/Elements('Q.58511')"
		},
		{
			"@id":"Dimensions('Company')/Hierarchies('Company')/Elements('58511')"
		},
		{
			"@id":"Dimensions('Company')/Hierarchies('Company')/Elements('58510')"
		},
		{
			"@id":"Dimensions('Company')/Hierarchies('Company')/Elements('Q.58030')"
		},
		{
			"@id":"Dimensions('Company')/Hierarchies('Company')/Elements('58030')"
		},
		{
			"@id":"Dimensions('Company')/Hierarchies('Company')/Elements('Q.58020')"
		},
		{
			"@id":"Dimensions('Company')/Hierarchies('Company')/Elements('58020')"
		},
		{
			"@id":"Dimensions('Company')/Hierarchies('Company')/Elements('Q.58010')"
		},
		{
			"@id":"Dimensions('Company')/Hierarchies('Company')/Elements('58010')"
		},
		{
			"@id":"Dimensions('Company')/Hierarchies('Company')/Elements('Q.57520')"
		},
		{
			"@id":"Dimensions('Company')/Hierarchies('Company')/Elements('57520')"
		},
		{
			"@id":"Dimensions('Company')/Hierarchies('Company')/Elements('Q.57510')"
		},
		{
			"@id":"Dimensions('Company')/Hierarchies('Company')/Elements('57510')"
		},
		{
			"@id":"Dimensions('Company')/Hierarchies('Company')/Elements('57420')"
		},
		{
			"@id":"Dimensions('Company')/Hierarchies('Company')/Elements('Q.57410')"
		},
		{
			"@id":"Dimensions('Company')/Hierarchies('Company')/Elements('57410')"
		},
		{
			"@id":"Dimensions('Company')/Hierarchies('Company')/Elements('57360')"
		},
		{
			"@id":"Dimensions('Company')/Hierarchies('Company')/Elements('57350')"
		},
		{
			"@id":"Dimensions('Company')/Hierarchies('Company')/Elements('57340')"
		},
		{
			"@id":"Dimensions('Company')/Hierarchies('Company')/Elements('57330')"
		},
		{
			"@id":"Dimensions('Company')/Hierarchies('Company')/Elements('Q.57320')"
		},
		{
			"@id":"Dimensions('Company')/Hierarchies('Company')/Elements('57320')"
		},
		{
			"@id":"Dimensions('Company')/Hierarchies('Company')/Elements('Q.57310')"
		},
		{
			"@id":"Dimensions('Company')/Hierarchies('Company')/Elements('57310')"
		},
		{
			"@id":"Dimensions('Company')/Hierarchies('Company')/Elements('Q.57195')"
		},
		{
			"@id":"Dimensions('Company')/Hierarchies('Company')/Elements('57195')"
		},
		{
			"@id":"Dimensions('Company')/Hierarchies('Company')/Elements('Q.57190')"
		},
		{
			"@id":"Dimensions('Company')/Hierarchies('Company')/Elements('57190')"
		},
		{
			"@id":"Dimensions('Company')/Hierarchies('Company')/Elements('Q.57180')"
		},
		{
			"@id":"Dimensions('Company')/Hierarchies('Company')/Elements('57180')"
		},
		{
			"@id":"Dimensions('Company')/Hierarchies('Company')/Elements('Q.57170')"
		},
		{
			"@id":"Dimensions('Company')/Hierarchies('Company')/Elements('57170')"
		},
		{
			"@id":"Dimensions('Company')/Hierarchies('Company')/Elements('57161')"
		},
		{
			"@id":"Dimensions('Company')/Hierarchies('Company')/Elements('Q.57160')"
		},
		{
			"@id":"Dimensions('Company')/Hierarchies('Company')/Elements('57160')"
		},
		{
			"@id":"Dimensions('Company')/Hierarchies('Company')/Elements('Q.57150')"
		},
		{
			"@id":"Dimensions('Company')/Hierarchies('Company')/Elements('57150')"
		},
		{
			"@id":"Dimensions('Company')/Hierarchies('Company')/Elements('Q.57140')"
		},
		{
			"@id":"Dimensions('Company')/Hierarchies('Company')/Elements('57140')"
		},
		{
			"@id":"Dimensions('Company')/Hierarchies('Company')/Elements('Q.57130')"
		},
		{
			"@id":"Dimensions('Company')/Hierarchies('Company')/Elements('57130')"
		},
		{
			"@id":"Dimensions('Company')/Hierarchies('Company')/Elements('Q.57121')"
		},
		{
			"@id":"Dimensions('Company')/Hierarchies('Company')/Elements('57121')"
		},
		{
			"@id":"Dimensions('Company')/Hierarchies('Company')/Elements('Q.57120')"
		},
		{
			"@id":"Dimensions('Company')/Hierarchies('Company')/Elements('57120')"
		},
		{
			"@id":"Dimensions('Company')/Hierarchies('Company')/Elements('Q.57110')"
		},
		{
			"@id":"Dimensions('Company')/Hierarchies('Company')/Elements('57110')"
		},
		{
			"@id":"Dimensions('Company')/Hierarchies('Company')/Elements('Q.57100')"
		},
		{
			"@id":"Dimensions('Company')/Hierarchies('Company')/Elements('57100')"
		},
		{
			"@id":"Dimensions('Company')/Hierarchies('Company')/Elements('Q.57011')"
		},
		{
			"@id":"Dimensions('Company')/Hierarchies('Company')/Elements('57011')"
		},
		{
			"@id":"Dimensions('Company')/Hierarchies('Company')/Elements('Q.57010')"
		},
		{
			"@id":"Dimensions('Company')/Hierarchies('Company')/Elements('57010')"
		},
		{
			"@id":"Dimensions('Company')/Hierarchies('Company')/Elements('Q.56090')"
		},
		{
			"@id":"Dimensions('Company')/Hierarchies('Company')/Elements('56090')"
		},
		{
			"@id":"Dimensions('Company')/Hierarchies('Company')/Elements('Q.56070')"
		},
		{
			"@id":"Dimensions('Company')/Hierarchies('Company')/Elements('56070')"
		},
		{
			"@id":"Dimensions('Company')/Hierarchies('Company')/Elements('Q.56060')"
		},
		{
			"@id":"Dimensions('Company')/Hierarchies('Company')/Elements('56060')"
		},
		{
			"@id":"Dimensions('Company')/Hierarchies('Company')/Elements('56050')"
		},
		{
			"@id":"Dimensions('Company')/Hierarchies('Company')/Elements('56040')"
		},
		{
			"@id":"Dimensions('Company')/Hierarchies('Company')/Elements('Q.56030')"
		},
		{
			"@id":"Dimensions('Company')/Hierarchies('Company')/Elements('56030')"
		},
		{
			"@id":"Dimensions('Company')/Hierarchies('Company')/Elements('56020')"
		},
		{
			"@id":"Dimensions('Company')/Hierarchies('Company')/Elements('Q.56010')"
		},
		{
			"@id":"Dimensions('Company')/Hierarchies('Company')/Elements('56010')"
		},
		{
			"@id":"Dimensions('Company')/Hierarchies('Company')/Elements('Q.55512')"
		},
		{
			"@id":"Dimensions('Company')/Hierarchies('Company')/Elements('55512')"
		},
		{
			"@id":"Dimensions('Company')/Hierarchies('Company')/Elements('Q.55511')"
		},
		{
			"@id":"Dimensions('Company')/Hierarchies('Company')/Elements('55511')"
		},
		{
			"@id":"Dimensions('Company')/Hierarchies('Company')/Elements('Q.55510')"
		},
		{
			"@id":"Dimensions('Company')/Hierarchies('Company')/Elements('55510')"
		},
		{
			"@id":"Dimensions('Company')/Hierarchies('Company')/Elements('54520')"
		},
		{
			"@id":"Dimensions('Company')/Hierarchies('Company')/Elements('54515')"
		},
		{
			"@id":"Dimensions('Company')/Hierarchies('Company')/Elements('Q.54514')"
		},
		{
			"@id":"Dimensions('Company')/Hierarchies('Company')/Elements('54514')"
		},
		{
			"@id":"Dimensions('Company')/Hierarchies('Company')/Elements('54513')"
		},
		{
			"@id":"Dimensions('Company')/Hierarchies('Company')/Elements('54512')"
		},
		{
			"@id":"Dimensions('Company')/Hierarchies('Company')/Elements('54511')"
		},
		{
			"@id":"Dimensions('Company')/Hierarchies('Company')/Elements('54510')"
		},
		{
			"@id":"Dimensions('Company')/Hierarchies('Company')/Elements('54020P')"
		},
		{
			"@id":"Dimensions('Company')/Hierarchies('Company')/Elements('Q.54020')"
		},
		{
			"@id":"Dimensions('Company')/Hierarchies('Company')/Elements('54020')"
		},
		{
			"@id":"Dimensions('Company')/Hierarchies('Company')/Elements('54010P')"
		},
		{
			"@id":"Dimensions('Company')/Hierarchies('Company')/Elements('Q.54010')"
		},
		{
			"@id":"Dimensions('Company')/Hierarchies('Company')/Elements('54010')"
		},
		{
			"@id":"Dimensions('Company')/Hierarchies('Company')/Elements('53130')"
		},
		{
			"@id":"Dimensions('Company')/Hierarchies('Company')/Elements('53120')"
		},
		{
			"@id":"Dimensions('Company')/Hierarchies('Company')/Elements('53110')"
		},
		{
			"@id":"Dimensions('Company')/Hierarchies('Company')/Elements('53040')"
		},
		{
			"@id":"Dimensions('Company')/Hierarchies('Company')/Elements('53030')"
		},
		{
			"@id":"Dimensions('Company')/Hierarchies('Company')/Elements('53020')"
		},
		{
			"@id":"Dimensions('Company')/Hierarchies('Company')/Elements('Q.53010')"
		},
		{
			"@id":"Dimensions('Company')/Hierarchies('Company')/Elements('53010')"
		},
		{
			"@id":"Dimensions('Company')/Hierarchies('Company')/Elements('Q.52120')"
		},
		{
			"@id":"Dimensions('Company')/Hierarchies('Company')/Elements('52120')"
		},
		{
			"@id":"Dimensions('Company')/Hierarchies('Company')/Elements('Q.52110')"
		},
		{
			"@id":"Dimensions('Company')/Hierarchies('Company')/Elements('52110')"
		},
		{
			"@id":"Dimensions('Company')/Hierarchies('Company')/Elements('Q.52080')"
		},
		{
			"@id":"Dimensions('Company')/Hierarchies('Company')/Elements('52080')"
		},
		{
			"@id":"Dimensions('Company')/Hierarchies('Company')/Elements('52060')"
		},
		{
			"@id":"Dimensions('Company')/Hierarchies('Company')/Elements('52050')"
		},
		{
			"@id":"Dimensions('Company')/Hierarchies('Company')/Elements('Q.52040')"
		},
		{
			"@id":"Dimensions('Company')/Hierarchies('Company')/Elements('52040')"
		},
		{
			"@id":"Dimensions('Company')/Hierarchies('Company')/Elements('Q.52030')"
		},
		{
			"@id":"Dimensions('Company')/Hierarchies('Company')/Elements('52030')"
		},
		{
			"@id":"Dimensions('Company')/Hierarchies('Company')/Elements('Q.52020')"
		},
		{
			"@id":"Dimensions('Company')/Hierarchies('Company')/Elements('52020')"
		},
		{
			"@id":"Dimensions('Company')/Hierarchies('Company')/Elements('Q.52010')"
		},
		{
			"@id":"Dimensions('Company')/Hierarchies('Company')/Elements('52010')"
		},
		{
			"@id":"Dimensions('Company')/Hierarchies('Company')/Elements('51930')"
		},
		{
			"@id":"Dimensions('Company')/Hierarchies('Company')/Elements('51920')"
		},
		{
			"@id":"Dimensions('Company')/Hierarchies('Company')/Elements('51910')"
		},
		{
			"@id":"Dimensions('Company')/Hierarchies('Company')/Elements('Q.51874')"
		},
		{
			"@id":"Dimensions('Company')/Hierarchies('Company')/Elements('51874')"
		},
		{
			"@id":"Dimensions('Company')/Hierarchies('Company')/Elements('Q.51873')"
		},
		{
			"@id":"Dimensions('Company')/Hierarchies('Company')/Elements('51873')"
		},
		{
			"@id":"Dimensions('Company')/Hierarchies('Company')/Elements('Q.51871')"
		},
		{
			"@id":"Dimensions('Company')/Hierarchies('Company')/Elements('51871')"
		},
		{
			"@id":"Dimensions('Company')/Hierarchies('Company')/Elements('Q.51870')"
		},
		{
			"@id":"Dimensions('Company')/Hierarchies('Company')/Elements('51870')"
		},
		{
			"@id":"Dimensions('Company')/Hierarchies('Company')/Elements('Q.51640')"
		},
		{
			"@id":"Dimensions('Company')/Hierarchies('Company')/Elements('51640')"
		},
		{
			"@id":"Dimensions('Company')/Hierarchies('Company')/Elements('Q.51540')"
		},
		{
			"@id":"Dimensions('Company')/Hierarchies('Company')/Elements('51540')"
		},
		{
			"@id":"Dimensions('Company')/Hierarchies('Company')/Elements('Q.51530')"
		},
		{
			"@id":"Dimensions('Company')/Hierarchies('Company')/Elements('51530')"
		},
		{
			"@id":"Dimensions('Company')/Hierarchies('Company')/Elements('Q.51520')"
		},
		{
			"@id":"Dimensions('Company')/Hierarchies('Company')/Elements('51520')"
		},
		{
			"@id":"Dimensions('Company')/Hierarchies('Company')/Elements('51471')"
		},
		{
			"@id":"Dimensions('Company')/Hierarchies('Company')/Elements('Q.51470')"
		},
		{
			"@id":"Dimensions('Company')/Hierarchies('Company')/Elements('51470')"
		},
		{
			"@id":"Dimensions('Company')/Hierarchies('Company')/Elements('Q.51469')"
		},
		{
			"@id":"Dimensions('Company')/Hierarchies('Company')/Elements('51469')"
		},
		{
			"@id":"Dimensions('Company')/Hierarchies('Company')/Elements('Q.51468')"
		},
		{
			"@id":"Dimensions('Company')/Hierarchies('Company')/Elements('51468')"
		},
		{
			"@id":"Dimensions('Company')/Hierarchies('Company')/Elements('Q.51467')"
		},
		{
			"@id":"Dimensions('Company')/Hierarchies('Company')/Elements('51467')"
		},
		{
			"@id":"Dimensions('Company')/Hierarchies('Company')/Elements('Q.51466')"
		},
		{
			"@id":"Dimensions('Company')/Hierarchies('Company')/Elements('51466')"
		},
		{
			"@id":"Dimensions('Company')/Hierarchies('Company')/Elements('Q.51465')"
		},
		{
			"@id":"Dimensions('Company')/Hierarchies('Company')/Elements('51465')"
		},
		{
			"@id":"Dimensions('Company')/Hierarchies('Company')/Elements('Q.51464')"
		},
		{
			"@id":"Dimensions('Company')/Hierarchies('Company')/Elements('51464')"
		},
		{
			"@id":"Dimensions('Company')/Hierarchies('Company')/Elements('Q.51463')"
		},
		{
			"@id":"Dimensions('Company')/Hierarchies('Company')/Elements('51463')"
		},
		{
			"@id":"Dimensions('Company')/Hierarchies('Company')/Elements('Q.51462')"
		},
		{
			"@id":"Dimensions('Company')/Hierarchies('Company')/Elements('51462')"
		},
		{
			"@id":"Dimensions('Company')/Hierarchies('Company')/Elements('Q.51461')"
		},
		{
			"@id":"Dimensions('Company')/Hierarchies('Company')/Elements('51461')"
		},
		{
			"@id":"Dimensions('Company')/Hierarchies('Company')/Elements('Q.51454')"
		},
		{
			"@id":"Dimensions('Company')/Hierarchies('Company')/Elements('51454')"
		},
		{
			"@id":"Dimensions('Company')/Hierarchies('Company')/Elements('51453')"
		},
		{
			"@id":"Dimensions('Company')/Hierarchies('Company')/Elements('Q.51452')"
		},
		{
			"@id":"Dimensions('Company')/Hierarchies('Company')/Elements('51452')"
		},
		{
			"@id":"Dimensions('Company')/Hierarchies('Company')/Elements('Q.51451')"
		},
		{
			"@id":"Dimensions('Company')/Hierarchies('Company')/Elements('51451')"
		},
		{
			"@id":"Dimensions('Company')/Hierarchies('Company')/Elements('Q.51431')"
		},
		{
			"@id":"Dimensions('Company')/Hierarchies('Company')/Elements('51431')"
		},
		{
			"@id":"Dimensions('Company')/Hierarchies('Company')/Elements('51426')"
		},
		{
			"@id":"Dimensions('Company')/Hierarchies('Company')/Elements('51425')"
		},
		{
			"@id":"Dimensions('Company')/Hierarchies('Company')/Elements('51423')"
		},
		{
			"@id":"Dimensions('Company')/Hierarchies('Company')/Elements('Q.51421')"
		},
		{
			"@id":"Dimensions('Company')/Hierarchies('Company')/Elements('51421')"
		},
		{
			"@id":"Dimensions('Company')/Hierarchies('Company')/Elements('Q.51420')"
		},
		{
			"@id":"Dimensions('Company')/Hierarchies('Company')/Elements('51420')"
		},
		{
			"@id":"Dimensions('Company')/Hierarchies('Company')/Elements('Q.51419')"
		},
		{
			"@id":"Dimensions('Company')/Hierarchies('Company')/Elements('51419')"
		},
		{
			"@id":"Dimensions('Company')/Hierarchies('Company')/Elements('51418')"
		},
		{
			"@id":"Dimensions('Company')/Hierarchies('Company')/Elements('Q.51417')"
		},
		{
			"@id":"Dimensions('Company')/Hierarchies('Company')/Elements('51417')"
		},
		{
			"@id":"Dimensions('Company')/Hierarchies('Company')/Elements('51416')"
		},
		{
			"@id":"Dimensions('Company')/Hierarchies('Company')/Elements('Q.51415')"
		},
		{
			"@id":"Dimensions('Company')/Hierarchies('Company')/Elements('51415')"
		},
		{
			"@id":"Dimensions('Company')/Hierarchies('Company')/Elements('Q.51414')"
		},
		{
			"@id":"Dimensions('Company')/Hierarchies('Company')/Elements('51414')"
		},
		{
			"@id":"Dimensions('Company')/Hierarchies('Company')/Elements('Q.51413')"
		},
		{
			"@id":"Dimensions('Company')/Hierarchies('Company')/Elements('51413')"
		},
		{
			"@id":"Dimensions('Company')/Hierarchies('Company')/Elements('Q.51412')"
		},
		{
			"@id":"Dimensions('Company')/Hierarchies('Company')/Elements('51412')"
		},
		{
			"@id":"Dimensions('Company')/Hierarchies('Company')/Elements('Q.51411')"
		},
		{
			"@id":"Dimensions('Company')/Hierarchies('Company')/Elements('51411')"
		},
		{
			"@id":"Dimensions('Company')/Hierarchies('Company')/Elements('Q.51410')"
		},
		{
			"@id":"Dimensions('Company')/Hierarchies('Company')/Elements('51410')"
		},
		{
			"@id":"Dimensions('Company')/Hierarchies('Company')/Elements('Q.51409')"
		},
		{
			"@id":"Dimensions('Company')/Hierarchies('Company')/Elements('51409')"
		},
		{
			"@id":"Dimensions('Company')/Hierarchies('Company')/Elements('Q.51408')"
		},
		{
			"@id":"Dimensions('Company')/Hierarchies('Company')/Elements('51408')"
		},
		{
			"@id":"Dimensions('Company')/Hierarchies('Company')/Elements('Q.51407')"
		},
		{
			"@id":"Dimensions('Company')/Hierarchies('Company')/Elements('51407')"
		},
		{
			"@id":"Dimensions('Company')/Hierarchies('Company')/Elements('51406')"
		},
		{
			"@id":"Dimensions('Company')/Hierarchies('Company')/Elements('51405')"
		},
		{
			"@id":"Dimensions('Company')/Hierarchies('Company')/Elements('Q.51404')"
		},
		{
			"@id":"Dimensions('Company')/Hierarchies('Company')/Elements('51404')"
		},
		{
			"@id":"Dimensions('Company')/Hierarchies('Company')/Elements('51403')"
		},
		{
			"@id":"Dimensions('Company')/Hierarchies('Company')/Elements('51402')"
		},
		{
			"@id":"Dimensions('Company')/Hierarchies('Company')/Elements('51401')"
		},
		{
			"@id":"Dimensions('Company')/Hierarchies('Company')/Elements('Q.51227')"
		},
		{
			"@id":"Dimensions('Company')/Hierarchies('Company')/Elements('51227')"
		},
		{
			"@id":"Dimensions('Company')/Hierarchies('Company')/Elements('Q.51226')"
		},
		{
			"@id":"Dimensions('Company')/Hierarchies('Company')/Elements('51226')"
		},
		{
			"@id":"Dimensions('Company')/Hierarchies('Company')/Elements('51225')"
		},
		{
			"@id":"Dimensions('Company')/Hierarchies('Company')/Elements('Q.51224')"
		},
		{
			"@id":"Dimensions('Company')/Hierarchies('Company')/Elements('51224')"
		},
		{
			"@id":"Dimensions('Company')/Hierarchies('Company')/Elements('Q.51222')"
		},
		{
			"@id":"Dimensions('Company')/Hierarchies('Company')/Elements('51222')"
		},
		{
			"@id":"Dimensions('Company')/Hierarchies('Company')/Elements('Q.51220')"
		},
		{
			"@id":"Dimensions('Company')/Hierarchies('Company')/Elements('51220')"
		},
		{
			"@id":"Dimensions('Company')/Hierarchies('Company')/Elements('51217')"
		},
		{
			"@id":"Dimensions('Company')/Hierarchies('Company')/Elements('51216')"
		},
		{
			"@id":"Dimensions('Company')/Hierarchies('Company')/Elements('Q.51215')"
		},
		{
			"@id":"Dimensions('Company')/Hierarchies('Company')/Elements('51215')"
		},
		{
			"@id":"Dimensions('Company')/Hierarchies('Company')/Elements('51214')"
		},
		{
			"@id":"Dimensions('Company')/Hierarchies('Company')/Elements('51213')"
		},
		{
			"@id":"Dimensions('Company')/Hierarchies('Company')/Elements('51212')"
		},
		{
			"@id":"Dimensions('Company')/Hierarchies('Company')/Elements('51210')"
		},
		{
			"@id":"Dimensions('Company')/Hierarchies('Company')/Elements('Q.51033')"
		},
		{
			"@id":"Dimensions('Company')/Hierarchies('Company')/Elements('51033')"
		},
		{
			"@id":"Dimensions('Company')/Hierarchies('Company')/Elements('Q.51032')"
		},
		{
			"@id":"Dimensions('Company')/Hierarchies('Company')/Elements('51032')"
		},
		{
			"@id":"Dimensions('Company')/Hierarchies('Company')/Elements('Q.51031')"
		},
		{
			"@id":"Dimensions('Company')/Hierarchies('Company')/Elements('51031')"
		},
		{
			"@id":"Dimensions('Company')/Hierarchies('Company')/Elements('Q.51020')"
		},
		{
			"@id":"Dimensions('Company')/Hierarchies('Company')/Elements('51020')"
		},
		{
			"@id":"Dimensions('Company')/Hierarchies('Company')/Elements('Q.51010')"
		},
		{
			"@id":"Dimensions('Company')/Hierarchies('Company')/Elements('51010')"
		},
		{
			"@id":"Dimensions('Company')/Hierarchies('Company')/Elements('Q.50512')"
		},
		{
			"@id":"Dimensions('Company')/Hierarchies('Company')/Elements('50512')"
		},
		{
			"@id":"Dimensions('Company')/Hierarchies('Company')/Elements('50511')"
		},
		{
			"@id":"Dimensions('Company')/Hierarchies('Company')/Elements('50140')"
		},
		{
			"@id":"Dimensions('Company')/Hierarchies('Company')/Elements('50130')"
		},
		{
			"@id":"Dimensions('Company')/Hierarchies('Company')/Elements('50120')"
		},
		{
			"@id":"Dimensions('Company')/Hierarchies('Company')/Elements('Q.50110')"
		},
		{
			"@id":"Dimensions('Company')/Hierarchies('Company')/Elements('50110')"
		},
		{
			"@id":"Dimensions('Company')/Hierarchies('Company')/Elements('Q.50100')"
		},
		{
			"@id":"Dimensions('Company')/Hierarchies('Company')/Elements('50100')"
		},
		{
			"@id":"Dimensions('Company')/Hierarchies('Company')/Elements('Q.50099')"
		},
		{
			"@id":"Dimensions('Company')/Hierarchies('Company')/Elements('50099')"
		},
		{
			"@id":"Dimensions('Company')/Hierarchies('Company')/Elements('Q.50090')"
		},
		{
			"@id":"Dimensions('Company')/Hierarchies('Company')/Elements('50090')"
		},
		{
			"@id":"Dimensions('Company')/Hierarchies('Company')/Elements('Q.50080')"
		},
		{
			"@id":"Dimensions('Company')/Hierarchies('Company')/Elements('50080')"
		},
		{
			"@id":"Dimensions('Company')/Hierarchies('Company')/Elements('Q.50072')"
		},
		{
			"@id":"Dimensions('Company')/Hierarchies('Company')/Elements('50072')"
		},
		{
			"@id":"Dimensions('Company')/Hierarchies('Company')/Elements('Q.50071')"
		},
		{
			"@id":"Dimensions('Company')/Hierarchies('Company')/Elements('50071')"
		},
		{
			"@id":"Dimensions('Company')/Hierarchies('Company')/Elements('Q.50070')"
		},
		{
			"@id":"Dimensions('Company')/Hierarchies('Company')/Elements('50070')"
		},
		{
			"@id":"Dimensions('Company')/Hierarchies('Company')/Elements('Q.50069')"
		},
		{
			"@id":"Dimensions('Company')/Hierarchies('Company')/Elements('50069')"
		},
		{
			"@id":"Dimensions('Company')/Hierarchies('Company')/Elements('50068')"
		},
		{
			"@id":"Dimensions('Company')/Hierarchies('Company')/Elements('50067')"
		},
		{
			"@id":"Dimensions('Company')/Hierarchies('Company')/Elements('50066')"
		},
		{
			"@id":"Dimensions('Company')/Hierarchies('Company')/Elements('50065')"
		},
		{
			"@id":"Dimensions('Company')/Hierarchies('Company')/Elements('Q.50062')"
		},
		{
			"@id":"Dimensions('Company')/Hierarchies('Company')/Elements('50062')"
		},
		{
			"@id":"Dimensions('Company')/Hierarchies('Company')/Elements('Q.50061')"
		},
		{
			"@id":"Dimensions('Company')/Hierarchies('Company')/Elements('50061')"
		},
		{
			"@id":"Dimensions('Company')/Hierarchies('Company')/Elements('Q.50060')"
		},
		{
			"@id":"Dimensions('Company')/Hierarchies('Company')/Elements('50060')"
		},
		{
			"@id":"Dimensions('Company')/Hierarchies('Company')/Elements('Q.50050')"
		},
		{
			"@id":"Dimensions('Company')/Hierarchies('Company')/Elements('50050')"
		},
		{
			"@id":"Dimensions('Company')/Hierarchies('Company')/Elements('50040')"
		},
		{
			"@id":"Dimensions('Company')/Hierarchies('Company')/Elements('Q.50033')"
		},
		{
			"@id":"Dimensions('Company')/Hierarchies('Company')/Elements('50033')"
		},
		{
			"@id":"Dimensions('Company')/Hierarchies('Company')/Elements('Q.50032')"
		},
		{
			"@id":"Dimensions('Company')/Hierarchies('Company')/Elements('50032')"
		},
		{
			"@id":"Dimensions('Company')/Hierarchies('Company')/Elements('50031')"
		},
		{
			"@id":"Dimensions('Company')/Hierarchies('Company')/Elements('Q.50030')"
		},
		{
			"@id":"Dimensions('Company')/Hierarchies('Company')/Elements('50030')"
		},
		{
			"@id":"Dimensions('Company')/Hierarchies('Company')/Elements('Q.50020')"
		},
		{
			"@id":"Dimensions('Company')/Hierarchies('Company')/Elements('50020')"
		},
		{
			"@id":"Dimensions('Company')/Hierarchies('Company')/Elements('Q.50010')"
		},
		{
			"@id":"Dimensions('Company')/Hierarchies('Company')/Elements('50010')"
		},
		{
			"@id":"Dimensions('Company')/Hierarchies('Company')/Elements('44900')"
		},
		{
			"@id":"Dimensions('Company')/Hierarchies('Company')/Elements('44800')"
		},
		{
			"@id":"Dimensions('Company')/Hierarchies('Company')/Elements('44700')"
		},
		{
			"@id":"Dimensions('Company')/Hierarchies('Company')/Elements('Q.44600')"
		},
		{
			"@id":"Dimensions('Company')/Hierarchies('Company')/Elements('44600')"
		},
		{
			"@id":"Dimensions('Company')/Hierarchies('Company')/Elements('Q.44500')"
		},
		{
			"@id":"Dimensions('Company')/Hierarchies('Company')/Elements('44500')"
		},
		{
			"@id":"Dimensions('Company')/Hierarchies('Company')/Elements('44400')"
		},
		{
			"@id":"Dimensions('Company')/Hierarchies('Company')/Elements('44300')"
		},
		{
			"@id":"Dimensions('Company')/Hierarchies('Company')/Elements('Q.44200')"
		},
		{
			"@id":"Dimensions('Company')/Hierarchies('Company')/Elements('44200')"
		},
		{
			"@id":"Dimensions('Company')/Hierarchies('Company')/Elements('44110')"
		},
		{
			"@id":"Dimensions('Company')/Hierarchies('Company')/Elements('44100')"
		},
		{
			"@id":"Dimensions('Company')/Hierarchies('Company')/Elements('43700')"
		},
		{
			"@id":"Dimensions('Company')/Hierarchies('Company')/Elements('43110')"
		},
		{
			"@id":"Dimensions('Company')/Hierarchies('Company')/Elements('43105')"
		},
		{
			"@id":"Dimensions('Company')/Hierarchies('Company')/Elements('43100')"
		},
		{
			"@id":"Dimensions('Company')/Hierarchies('Company')/Elements('Q.43095')"
		},
		{
			"@id":"Dimensions('Company')/Hierarchies('Company')/Elements('43095')"
		},
		{
			"@id":"Dimensions('Company')/Hierarchies('Company')/Elements('Q.43093')"
		},
		{
			"@id":"Dimensions('Company')/Hierarchies('Company')/Elements('43093')"
		},
		{
			"@id":"Dimensions('Company')/Hierarchies('Company')/Elements('Q.43092')"
		},
		{
			"@id":"Dimensions('Company')/Hierarchies('Company')/Elements('43092')"
		},
		{
			"@id":"Dimensions('Company')/Hierarchies('Company')/Elements('Q.43091')"
		},
		{
			"@id":"Dimensions('Company')/Hierarchies('Company')/Elements('43091')"
		},
		{
			"@id":"Dimensions('Company')/Hierarchies('Company')/Elements('Q.43090')"
		},
		{
			"@id":"Dimensions('Company')/Hierarchies('Company')/Elements('43090')"
		},
		{
			"@id":"Dimensions('Company')/Hierarchies('Company')/Elements('Q.43080')"
		},
		{
			"@id":"Dimensions('Company')/Hierarchies('Company')/Elements('43080')"
		},
		{
			"@id":"Dimensions('Company')/Hierarchies('Company')/Elements('43075')"
		},
		{
			"@id":"Dimensions('Company')/Hierarchies('Company')/Elements('43071')"
		},
		{
			"@id":"Dimensions('Company')/Hierarchies('Company')/Elements('43070')"
		},
		{
			"@id":"Dimensions('Company')/Hierarchies('Company')/Elements('43066')"
		},
		{
			"@id":"Dimensions('Company')/Hierarchies('Company')/Elements('43065')"
		},
		{
			"@id":"Dimensions('Company')/Hierarchies('Company')/Elements('Q.43062')"
		},
		{
			"@id":"Dimensions('Company')/Hierarchies('Company')/Elements('43062')"
		},
		{
			"@id":"Dimensions('Company')/Hierarchies('Company')/Elements('Q.43061')"
		},
		{
			"@id":"Dimensions('Company')/Hierarchies('Company')/Elements('43061')"
		},
		{
			"@id":"Dimensions('Company')/Hierarchies('Company')/Elements('Q.43060')"
		},
		{
			"@id":"Dimensions('Company')/Hierarchies('Company')/Elements('43060')"
		},
		{
			"@id":"Dimensions('Company')/Hierarchies('Company')/Elements('43055')"
		},
		{
			"@id":"Dimensions('Company')/Hierarchies('Company')/Elements('Q.43050')"
		},
		{
			"@id":"Dimensions('Company')/Hierarchies('Company')/Elements('43050')"
		},
		{
			"@id":"Dimensions('Company')/Hierarchies('Company')/Elements('43045')"
		},
		{
			"@id":"Dimensions('Company')/Hierarchies('Company')/Elements('Q.43040')"
		},
		{
			"@id":"Dimensions('Company')/Hierarchies('Company')/Elements('43040')"
		},
		{
			"@id":"Dimensions('Company')/Hierarchies('Company')/Elements('Q.43030')"
		},
		{
			"@id":"Dimensions('Company')/Hierarchies('Company')/Elements('43030')"
		},
		{
			"@id":"Dimensions('Company')/Hierarchies('Company')/Elements('Q.43020')"
		},
		{
			"@id":"Dimensions('Company')/Hierarchies('Company')/Elements('43020')"
		},
		{
			"@id":"Dimensions('Company')/Hierarchies('Company')/Elements('43010')"
		},
		{
			"@id":"Dimensions('Company')/Hierarchies('Company')/Elements('Q.42220')"
		},
		{
			"@id":"Dimensions('Company')/Hierarchies('Company')/Elements('42220')"
		},
		{
			"@id":"Dimensions('Company')/Hierarchies('Company')/Elements('Q.42210')"
		},
		{
			"@id":"Dimensions('Company')/Hierarchies('Company')/Elements('42210')"
		},
		{
			"@id":"Dimensions('Company')/Hierarchies('Company')/Elements('Q.42140')"
		},
		{
			"@id":"Dimensions('Company')/Hierarchies('Company')/Elements('42140')"
		},
		{
			"@id":"Dimensions('Company')/Hierarchies('Company')/Elements('Q.42130')"
		},
		{
			"@id":"Dimensions('Company')/Hierarchies('Company')/Elements('42130')"
		},
		{
			"@id":"Dimensions('Company')/Hierarchies('Company')/Elements('Q.42120')"
		},
		{
			"@id":"Dimensions('Company')/Hierarchies('Company')/Elements('42120')"
		},
		{
			"@id":"Dimensions('Company')/Hierarchies('Company')/Elements('42110')"
		},
		{
			"@id":"Dimensions('Company')/Hierarchies('Company')/Elements('42030')"
		},
		{
			"@id":"Dimensions('Company')/Hierarchies('Company')/Elements('42020')"
		},
		{
			"@id":"Dimensions('Company')/Hierarchies('Company')/Elements('Q.42010')"
		},
		{
			"@id":"Dimensions('Company')/Hierarchies('Company')/Elements('42010')"
		},
		{
			"@id":"Dimensions('Company')/Hierarchies('Company')/Elements('Q.41199')"
		},
		{
			"@id":"Dimensions('Company')/Hierarchies('Company')/Elements('41199')"
		},
		{
			"@id":"Dimensions('Company')/Hierarchies('Company')/Elements('41130')"
		},
		{
			"@id":"Dimensions('Company')/Hierarchies('Company')/Elements('41120')"
		},
		{
			"@id":"Dimensions('Company')/Hierarchies('Company')/Elements('41110')"
		},
		{
			"@id":"Dimensions('Company')/Hierarchies('Company')/Elements('Q.41100')"
		},
		{
			"@id":"Dimensions('Company')/Hierarchies('Company')/Elements('41100')"
		},
		{
			"@id":"Dimensions('Company')/Hierarchies('Company')/Elements('41090')"
		},
		{
			"@id":"Dimensions('Company')/Hierarchies('Company')/Elements('41070')"
		},
		{
			"@id":"Dimensions('Company')/Hierarchies('Company')/Elements('Q.41060')"
		},
		{
			"@id":"Dimensions('Company')/Hierarchies('Company')/Elements('41060')"
		},
		{
			"@id":"Dimensions('Company')/Hierarchies('Company')/Elements('41050')"
		},
		{
			"@id":"Dimensions('Company')/Hierarchies('Company')/Elements('41030')"
		},
		{
			"@id":"Dimensions('Company')/Hierarchies('Company')/Elements('41020')"
		},
		{
			"@id":"Dimensions('Company')/Hierarchies('Company')/Elements('41010')"
		},
		{
			"@id":"Dimensions('Company')/Hierarchies('Company')/Elements('Q.40200')"
		},
		{
			"@id":"Dimensions('Company')/Hierarchies('Company')/Elements('40200')"
		},
		{
			"@id":"Dimensions('Company')/Hierarchies('Company')/Elements('40100')"
		},
		{
			"@id":"Dimensions('Company')/Hierarchies('Company')/Elements('21160')"
		},
		{
			"@id":"Dimensions('Company')/Hierarchies('Company')/Elements('Q.21150')"
		},
		{
			"@id":"Dimensions('Company')/Hierarchies('Company')/Elements('21150')"
		},
		{
			"@id":"Dimensions('Company')/Hierarchies('Company')/Elements('Q.21120')"
		},
		{
			"@id":"Dimensions('Company')/Hierarchies('Company')/Elements('21120')"
		},
		{
			"@id":"Dimensions('Company')/Hierarchies('Company')/Elements('21110')"
		},
		{
			"@id":"Dimensions('Company')/Hierarchies('Company')/Elements('21050')"
		},
		{
			"@id":"Dimensions('Company')/Hierarchies('Company')/Elements('21040')"
		},
		{
			"@id":"Dimensions('Company')/Hierarchies('Company')/Elements('21020')"
		},
		{
			"@id":"Dimensions('Company')/Hierarchies('Company')/Elements('20040')"
		},
		{
			"@id":"Dimensions('Company')/Hierarchies('Company')/Elements('20031')"
		},
		{
			"@id":"Dimensions('Company')/Hierarchies('Company')/Elements('20030')"
		},
		{
			"@id":"Dimensions('Company')/Hierarchies('Company')/Elements('20020')"
		},
		{
			"@id":"Dimensions('Company')/Hierarchies('Company')/Elements('20010')"
		},
		{
			"@id":"Dimensions('Company')/Hierarchies('Company')/Elements('Q.10700')"
		},
		{
			"@id":"Dimensions('Company')/Hierarchies('Company')/Elements('10700')"
		},
		{
			"@id":"Dimensions('Company')/Hierarchies('Company')/Elements('10610')"
		},
		{
			"@id":"Dimensions('Company')/Hierarchies('Company')/Elements('10600')"
		},
		{
			"@id":"Dimensions('Company')/Hierarchies('Company')/Elements('10511')"
		},
		{
			"@id":"Dimensions('Company')/Hierarchies('Company')/Elements('10510')"
		},
		{
			"@id":"Dimensions('Company')/Hierarchies('Company')/Elements('10500')"
		},
		{
			"@id":"Dimensions('Company')/Hierarchies('Company')/Elements('Q.10400')"
		},
		{
			"@id":"Dimensions('Company')/Hierarchies('Company')/Elements('10400')"
		},
		{
			"@id":"Dimensions('Company')/Hierarchies('Company')/Elements('10300')"
		},
		{
			"@id":"Dimensions('Company')/Hierarchies('Company')/Elements('10200')"
		},
		{
			"@id":"Dimensions('Company')/Hierarchies('Company')/Elements('10100')"
		},
		{
			"@id":"Dimensions('Company')/Hierarchies('Company')/Elements('10011')"
		},
		{
			"@id":"Dimensions('Company')/Hierarchies('Company')/Elements('10010')"
		}
	]
}